Workbook

Sheet Cap Table
A1: Capitalization Table
A2: Share Price | B2: =Valuation!B6 -> 472.89
A3: Shares Outstanding Build
A4: Basic Shares Outstanding | B4: =SUM(B5:B6) -> 205.5842
A5: Issued ordinary shares | B5: 210.24127
A6: (–) Treasury shares | B6: -4.657063
A7: RSUs | B7: 1.456016
A8: Option Build
A9: Options | B9: 4.496814
A10: Average Option Strike Price | B10: 256.44
A11: Net New Shares Created by Options | B11: =MAX(0,B9*(B2-B10)/B2) -> 2.0582702
A12: Total Diluted Shares Outstanding | B12: =B4+B7+B11 -> 209.09849
A13: Market Cap (in Millions) | B13: =B2*B12 -> 98880.585
A14: (+) Debt | B14: =(Model!O50+Model!O60)*Valuation!B7 -> 0
A15: (–) Cash & Short-Term Investments | B15: =(Model!O39+Model!O40)*Valuation!B7 -> 10569.949
A16: Enterprise Value | B16: =B13+B14-B15 -> 88310.636
A17: LTM EV / Sales | B17: =B16/(SUM(Model!L5:O5)*Valuation!B7) -> 4.3303481
A18: LTM EV / EBITDA | B18: =B16/((SUM(Model!L13:O13)+SUM(Model!L71:O71)+SUM(Model!L72:O72))*Valuation!B7) -> 28.449617

Sheet Model
A1: SPOT Quarterly Three-Statement Model (€m, except per-share data and shares)
A2: Period | B2: Q1-2023 | C2: Q2-2023 | D2: Q3-2023 | E2: Q4-2023 | F2: Q1-2024 | G2: Q2-2024 | H2: Q3-2024 | I2: Q4-2024 | J2: Q1-2025 | K2: Q2-2025 | L2: Q3-2025 | M2: Q4-2025 | N2: Q1-2026 | O2: Q2-2026 | P2: Q3-2026E | Q2: Q4-2026E | R2: Q1-2027E | S2: Q2-2027E | U2: FY2023 | V2: FY2024 | W2: FY2025 | X2: FY2026E | Y2: NTM Q2-27
A4: Income Statement
A5: Revenue | B5: 3042 | C5: 3177 | D5: 3357 | E5: ='Raw Numbers'!$B$4-SUM(B5:D5) -> 3671 | F5: 3636 | G5: 3807 | H5: 3988 | I5: ='Raw Numbers'!$C$4-SUM(F5:H5) -> 4242 | J5: 4190 | K5: 4193 | L5: 4272 | M5: ='Raw Numbers'!$D$4-SUM(J5:L5) -> 4531 | N5: 4533 | O5: 4777 | P5: =Assumptions!B4 -> 5000 | Q5: =M5*(1+Assumptions!C5) -> 5029.41 | R5: =N5*(1+Assumptions!D5) -> 4986.3 | S5: =O5*(1+Assumptions!E5) -> 5254.7 | U5: =SUM(B5,C5,D5,E5) -> 13247 | V5: =SUM(F5,G5,H5,I5) -> 15673 | W5: =SUM(J5,K5,L5,M5) -> 17186 | X5: =SUM(N5,O5,P5,Q5) -> 19339.41 | Y5: =SUM(P5,Q5,R5,S5) -> 20270.41
A6: Cost of revenue | B6: 2276 | C6: 2411 | D6: 2472 | E6: ='Raw Numbers'!$B$5-SUM(B6:D6) -> 2691 | F6: 2632 | G6: 2695 | H6: 2748 | I6: ='Raw Numbers'!$C$5-SUM(F6:H6) -> 2874 | J6: 2864 | K6: 2873 | L6: 2921 | M6: ='Raw Numbers'!$D$5-SUM(J6:L6) -> 3032 | N6: 3038 | O6: 3181 | P6: =P5-P7 -> 3355 | Q6: =Q5-Q7 -> 3384.7929 | R6: =R5-R7 -> 3350.7936 | S6: =S5-S7 -> 3525.9037 | U6: =SUM(B6,C6,D6,E6) -> 9850 | V6: =SUM(F6,G6,H6,I6) -> 10949 | W6: =SUM(J6,K6,L6,M6) -> 11690 | X6: =SUM(N6,O6,P6,Q6) -> 12958.793 | Y6: =SUM(P6,Q6,R6,S6) -> 13616.49
A7: Gross profit | B7: =B5-B6 -> 766 | C7: =C5-C6 -> 766 | D7: =D5-D6 -> 885 | E7: =E5-E6 -> 980 | F7: =F5-F6 -> 1004 | G7: =G5-G6 -> 1112 | H7: =H5-H6 -> 1240 | I7: =I5-I6 -> 1368 | ... O7: =O5-O6 -> 1596 | P7: =P5*Assumptions!B6 -> 1645 | Q7: =Q5*Assumptions!C6 -> 1644.6171 | R7: =R5*Assumptions!D6 -> 1635.5064 | S7: =S5*Assumptions!E6 -> 1728.7963 | U7: =SUM(B7,C7,D7,E7) -> 3397 | V7: =SUM(F7,G7,H7,I7) -> 4724 | W7: =SUM(J7,K7,L7,M7) -> 5496 | X7: =SUM(N7,O7,P7,Q7) -> 6380.6171 | Y7: =SUM(P7,Q7,R7,S7) -> 6653.9198
A8: Gross margin | B8: =B7/B5 -> 0.25180802 | C8: =C7/C5 -> 0.24110796 | D8: =D7/D5 -> 0.26362824 | E8: =E7/E5 -> 0.26695723 | F8: =F7/F5 -> 0.27612761 | G8: =G7/G5 -> 0.29209351 | H8: =H7/H5 -> 0.3109328 | I8: =I7/I5 -> 0.32248939 | ... S8: =S7/S5 -> 0.329 | U8: =U7/U5 -> 0.25643542 | V8: =V7/V5 -> 0.30141007 | W8: =W7/W5 -> 0.31979518 | X8: =X7/X5 -> 0.32992822 | Y8: =Y7/Y5 -> 0.32825778
A9: Research and development | B9: 435 | C9: 453 | D9: 369 | E9: ='Raw Numbers'!$B$7-SUM(B9:D9) -> 468 | F9: 389 | G9: 379 | H9: 342 | I9: ='Raw Numbers'!$C$7-SUM(F9:H9) -> 376 | J9: 379 | K9: 415 | L9: 309 | M9: ='Raw Numbers'!$D$7-SUM(J9:L9) -> 290 | N9: 331 | O9: 403 | P9: =(P7-Assumptions!B7)*Assumptions!B8 -> 409.5 | Q9: =Q5*Assumptions!C11 -> 377.20575 | R9: =R5*Assumptions!D11 -> 378.9588 | S9: =S5*Assumptions!E11 -> 409.8666 | U9: =SUM(B9,C9,D9,E9) -> 1725 | V9: =SUM(F9,G9,H9,I9) -> 1486 | W9: =SUM(J9,K9,L9,M9) -> 1393 | X9: =SUM(N9,O9,P9,Q9) -> 1520.7058 | Y9: =SUM(P9,Q9,R9,S9) -> 1575.5312
A10: Sales and marketing | B10: 347 | C10: 399 | D10: 355 | E10: ='Raw Numbers'!$B$8-SUM(B10:D10) -> 432 | F10: 324 | G10: 343 | H10: 332 | I10: ='Raw Numbers'!$C$8-SUM(F10:H10) -> 393 | J10: 314 | K10: 364 | L10: 349 | M10: ='Raw Numbers'!$D$8-SUM(J10:L10) -> 399 | N10: 342 | O10: 390 | P10: =(P7-Assumptions!B7)*Assumptions!B9 -> 409.5 | Q10: =Q5*Assumptions!C12 -> 402.3528 | R10: =R5*Assumptions!D12 -> 398.904 | S10: =S5*Assumptions!E12 -> 420.376 | U10: =SUM(B10,C10,D10,E10) -> 1533 | V10: =SUM(F10,G10,H10,I10) -> 1392 | W10: =SUM(J10,K10,L10,M10) -> 1426 | X10: =SUM(N10,O10,P10,Q10) -> 1543.8528 | Y10: =SUM(P10,Q10,R10,S10) -> 1631.1328
A11: General and administrative | B11: 140 | C11: 161 | D11: 129 | E11: ='Raw Numbers'!$B$9-SUM(B11:D11) -> 155 | F11: 123 | G11: 124 | H11: 112 | I11: ='Raw Numbers'!$C$9-SUM(F11:H11) -> 122 | J11: 124 | K11: 135 | L11: 111 | M11: ='Raw Numbers'!$D$9-SUM(J11:L11) -> 109 | N11: 107 | O11: 148 | P11: =(P7-Assumptions!B7)*Assumptions!B10 -> 156 | Q11: =Q5*Assumptions!C13 -> 130.76466 | R11: =R5*Assumptions!D13 -> 129.6438 | S11: =S5*Assumptions!E13 -> 141.8769 | U11: =SUM(B11,C11,D11,E11) -> 585 | V11: =SUM(F11,G11,H11,I11) -> 481 | W11: =SUM(J11,K11,L11,M11) -> 479 | X11: =SUM(N11,O11,P11,Q11) -> 541.76466 | Y11: =SUM(P11,Q11,R11,S11) -> 558.28536
A12: Total operating expenses | B12: =SUM(B9:B11) -> 922 | C12: =SUM(C9:C11) -> 1013 | D12: =SUM(D9:D11) -> 853 | E12: =SUM(E9:E11) -> 1055 | F12: =SUM(F9:F11) -> 836 | G12: =SUM(G9:G11) -> 846 | H12: =SUM(H9:H11) -> 786 | I12: =SUM(I9:I11) -> 891 | ... S12: =SUM(S9:S11) -> 972.1195 | U12: =SUM(B12,C12,D12,E12) -> 3843 | V12: =SUM(F12,G12,H12,I12) -> 3359 | W12: =SUM(J12,K12,L12,M12) -> 3298 | X12: =SUM(N12,O12,P12,Q12) -> 3606.3232 | Y12: =SUM(P12,Q12,R12,S12) -> 3764.9493
A13: Operating income/(loss) | B13: =B7-B12 -> -156 | C13: =C7-C12 -> -247 | D13: =D7-D12 -> 32 | E13: =E7-E12 -> -75 | F13: =F7-F12 -> 168 | G13: =G7-G12 -> 266 | H13: =H7-H12 -> 454 | I13: =I7-I12 -> 477 | ... S13: =S7-S12 -> 756.6768 | U13: =SUM(B13,C13,D13,E13) -> -446 | V13: =SUM(F13,G13,H13,I13) -> 1365 | W13: =SUM(J13,K13,L13,M13) -> 2198 | X13: =SUM(N13,O13,P13,Q13) -> 2774.2939 | Y13: =SUM(P13,Q13,R13,S13) -> 2888.9705
A14: Operating margin | B14: =B13/B5 -> -0.051282051 | C14: =C13/C5 -> -0.077746302 | D14: =D13/D5 -> 0.0095323205 | E14: =E13/E5 -> -0.0204304 | F14: =F13/F5 -> 0.04620462 | G14: =G13/G5 -> 0.06987129 | H14: =H13/H5 -> 0.11384152 | I14: =I13/I5 -> 0.11244696 | ... S14: =S13/S5 -> 0.144 | U14: =U13/U5 -> -0.033668 | V14: =V13/V5 -> 0.087092452 | W14: =W13/W5 -> 0.1278948 | X14: =X13/X5 -> 0.14345287 | Y14: =Y13/Y5 -> 0.14252156
A15: Finance income | B15: 27 | C15: 33 | D15: 55 | E15: ='Raw Numbers'!$B$12-SUM(B15:D15) -> 46 | F15: 59 | G15: 76 | H15: 66 | I15: ='Raw Numbers'!$C$12-SUM(F15:H15) -> 127 | J15: 71 | K15: 89 | L15: 262 | M15: ='Raw Numbers'!$D$12-SUM(J15:L15) -> -130 | N15: 248 | O15: 86 | P15: =(O40+O39)*Assumptions!B14/4 -> 82.145 | Q15: =(P40+P39)*Assumptions!C14/4 -> 86.825352 | R15: =(Q40+Q39)*Assumptions!D14/4 -> 90.442361 | S15: =(R40+R39)*Assumptions!E14/4 -> 93.479336 | U15: =SUM(B15,C15,D15,E15) -> 161 | V15: =SUM(F15,G15,H15,I15) -> 328 | W15: =SUM(J15,K15,L15,M15) -> 292 | X15: =SUM(N15,O15,P15,Q15) -> 502.97035 | Y15: =SUM(P15,Q15,R15,S15) -> 352.89205
A16: Finance costs | B16: -77 | C16: -27 | D16: -14 | E16: ='Raw Numbers'!$B$13-SUM(B16:D16) -> -102 | F16: -53 | G16: -72 | H16: -122 | I16: ='Raw Numbers'!$C$13-SUM(F16:H16) -> -105 | J16: -252 | K16: -447 | L16: -17 | M16: ='Raw Numbers'!$D$13-SUM(J16:L16) -> 450 | N16: -26 | O16: -21 | P16: =-P5*Assumptions!B15 -> -22.5 | Q16: =-Q5*Assumptions!C15 -> -22.632345 | R16: =-R5*Assumptions!D15 -> -22.43835 | S16: =-S5*Assumptions!E15 -> -23.64615 | U16: =SUM(B16,C16,D16,E16) -> -220 | V16: =SUM(F16,G16,H16,I16) -> -352 | W16: =SUM(J16,K16,L16,M16) -> -266 | X16: =SUM(N16,O16,P16,Q16) -> -92.132345 | Y16: =SUM(P16,Q16,R16,S16) -> -91.216845
A17: Finance income/(costs) - net | B17: =SUM(B15:B16) -> -50 | C17: =SUM(C15:C16) -> 6 | D17: =SUM(D15:D16) -> 41 | E17: =SUM(E15:E16) -> -56 | F17: =SUM(F15:F16) -> 6 | G17: =SUM(G15:G16) -> 4 | H17: =SUM(H15:H16) -> -56 | I17: =SUM(I15:I16) -> 22 | ... S17: =SUM(S15:S16) -> 69.833186 | U17: =SUM(B17,C17,D17,E17) -> -59 | V17: =SUM(F17,G17,H17,I17) -> -24 | W17: =SUM(J17,K17,L17,M17) -> 26 | X17: =SUM(N17,O17,P17,Q17) -> 410.83801 | Y17: =SUM(P17,Q17,R17,S17) -> 261.6752
A18: Income/(loss) before tax | B18: =B13+B17 -> -206 | C18: =C13+C17 -> -241 | D18: =D13+D17 -> 73 | E18: =E13+E17 -> -131 | F18: =F13+F17 -> 174 | G18: =G13+G17 -> 270 | H18: =H13+H17 -> 398 | I18: =I13+I17 -> 499 | ... S18: =S13+S17 -> 826.50999 | U18: =SUM(B18,C18,D18,E18) -> -505 | V18: =SUM(F18,G18,H18,I18) -> 1341 | W18: =SUM(J18,K18,L18,M18) -> 2224 | X18: =SUM(N18,O18,P18,Q18) -> 3185.1319 | Y18: =SUM(P18,Q18,R18,S18) -> 3150.6457
A19: Income tax expense/(benefit) | B19: 19 | C19: 61 | D19: 8 | E19: ='Raw Numbers'!$B$16-SUM(B19:D19) -> -61 | F19: -23 | G19: -4 | H19: 98 | I19: ='Raw Numbers'!$C$16-SUM(F19:H19) -> 132 | J19: 103 | K19: 134 | L19: -72 | M19: ='Raw Numbers'!$D$16-SUM(J19:L19) -> -153 | N19: 216 | O19: 175 | P19: =MAX(0,P18*Assumptions!B16) -> 175.1148 | Q19: =MAX(0,Q18*Assumptions!C16) -> 191.63685 | R19: =MAX(0,R18*Assumptions!D16) -> 191.04091 | S19: =MAX(0,S18*Assumptions!E16) -> 198.3624 | U19: =SUM(B19,C19,D19,E19) -> 27 | V19: =SUM(F19,G19,H19,I19) -> 203 | W19: =SUM(J19,K19,L19,M19) -> 12 | X19: =SUM(N19,O19,P19,Q19) -> 757.75165 | Y19: =SUM(P19,Q19,R19,S19) -> 756.15496
A20: Net income/(loss) | B20: =B18-B19 -> -225 | C20: =C18-C19 -> -302 | D20: =D18-D19 -> 65 | E20: =E18-E19 -> -70 | F20: =F18-F19 -> 197 | G20: =G18-G19 -> 274 | H20: =H18-H19 -> 300 | I20: =I18-I19 -> 367 | ... S20: =S18-S19 -> 628.14759 | U20: =SUM(B20,C20,D20,E20) -> -532 | V20: =SUM(F20,G20,H20,I20) -> 1138 | W20: =SUM(J20,K20,L20,M20) -> 2212 | X20: =SUM(N20,O20,P20,Q20) -> 2427.3802 | Y20: =SUM(P20,Q20,R20,S20) -> 2394.4907
A21: Basic EPS | B21: -1.16 | C21: -1.55 | D21: 0.33 | E21: =E20/E23 -> -0.35702463 | F21: 0.99 | G21: 1.37 | H21: 1.49 | I21: =I20/I23 -> 1.8085065 | J21: 1.1 | K21: -0.42 | L21: 4.36 | M21: =M20/M23 -> 5.7047789 | N21: 3.5 | O21: 2.65 | P21: =P20/P23 -> 2.6946642 | Q21: =Q20/Q23 -> 2.9489052 | R21: =R20/R23 -> 2.939735 | S21: =S20/S23 -> 3.0523979 | U21: ='Raw Numbers'!$B$18 -> -2.73 | V21: ='Raw Numbers'!$C$18 -> 5.67 | W21: ='Raw Numbers'!$D$18 -> 10.77 | X21: =X20/X23 -> 11.796547 | Y21: =Y20/Y23 -> 11.635702
A22: Diluted EPS | B22: -1.16 | C22: -1.55 | D22: 0.33 | E22: =IF(E20<0,E21,E20/E24) -> -0.35702463 | F22: 0.97 | G22: 1.33 | H22: 1.45 | I22: =IF(I20<0,I21,I20/I24) -> 1.7420686 | J22: 1.07 | K22: -0.42 | L22: 3.28 | M22: =IF(M20<0,M21,M20/M24) -> 5.5227182 | N22: 3.45 | O22: 2.61 | P22: =P20/P24 -> 2.6546741 | Q22: =Q20/Q24 -> 2.9051421 | R22: =R20/R24 -> 2.896108 | S22: =S20/S24 -> 3.0070988 | U22: ='Raw Numbers'!$B$19 -> -2.73 | V22: ='Raw Numbers'!$C$19 -> 5.5 | W22: ='Raw Numbers'!$D$19 -> 10.51 | X22: =X20/X24 -> 11.615435 | Y22: =Y20/Y24 -> 11.463023
A23: Weighted-average basic shares | B23: 193.56246 | C23: 194.42013 | D23: 194.88172 | E23: =4*'Raw Numbers'!$B$20-SUM(B23:D23) -> 196.0649 | F23: 198.02546 | G23: 199.95917 | H23: 201.57557 | I23: =4*'Raw Numbers'!$C$20-SUM(F23:H23) -> 202.92988 | J23: 204.46793 | K23: 205.427 | L23: 205.9645 | M23: =4*'Raw Numbers'!$D$20-SUM(J23:L23) -> 205.79237 | N23: 205.71685 | O23: 205.78824 | P23: =O23+Assumptions!B17 -> 205.78824 | Q23: =P23+Assumptions!C17 -> 205.78824 | R23: =Q23+Assumptions!D17 -> 205.78824 | S23: =R23+Assumptions!E17 -> 205.78824 | U23: ='Raw Numbers'!$B$20 -> 194.7323 | V23: ='Raw Numbers'!$C$20 -> 200.62252 | W23: ='Raw Numbers'!$D$20 -> 205.41295 | X23: =AVERAGE(N23,O23,P23,Q23) -> 205.77039 | Y23: =AVERAGE(P23,Q23,R23,S23) -> 205.78824
A24: Weighted-average diluted shares | B24: 193.56246 | C24: 194.42013 | D24: 198.01237 | E24: =E23 -> 196.0649 | F24: 203.77304 | G24: 206.11985 | H24: 207.3995 | I24: =4*'Raw Numbers'!$C$21-SUM(F24:H24) -> 210.66908 | J24: 210.24348 | K24: 205.427 | L24: 213.78974 | M24: =4*'Raw Numbers'!$D$21-SUM(J24:L24) -> 212.57648 | N24: 209.28045 | O24: 208.85847 | P24: =P23+Assumptions!B18 -> 208.88824 | Q24: =Q23+Assumptions!C18 -> 208.88824 | R24: =R23+Assumptions!D18 -> 208.88824 | S24: =S23+Assumptions!E18 -> 208.88824 | U24: ='Raw Numbers'!$B$21 -> 194.7323 | V24: ='Raw Numbers'!$C$21 -> 206.99037 | W24: ='Raw Numbers'!$D$21 -> 210.50917 | X24: =AVERAGE(N24,O24,P24,Q24) -> 208.97885 | Y24: =AVERAGE(P24,Q24,R24,S24) -> 208.88824
A27: Balance Sheet
A28: Lease right-of-use assets | B28: 413 | C28: 344 | D28: 343 | E28: 300 | F28: 274 | G28: 254 | H28: 235 | I28: 226 | J28: 223 | K28: 256 | L28: 242 | M28: 234 | N28: 227 | O28: 225 | P28: =O28*(1+Assumptions!B29) -> 222.75 | Q28: =P28*(1+Assumptions!C29) -> 220.5225 | R28: =Q28*(1+Assumptions!D29) -> 218.31727 | S28: =R28*(1+Assumptions!E29) -> 216.1341 | U28: =E28 -> 300 | V28: =I28 -> 226 | W28: =M28 -> 234 | X28: =Q28 -> 220.5225 | Y28: =S28 -> 216.1341
A29: Property & equipment | B29: 331 | C29: 280 | D29: 275 | E29: 247 | F29: 224 | G29: 211 | H29: 195 | I29: 188 | J29: 178 | K29: 161 | L29: 174 | M29: 188 | N29: 182 | O29: 193 | P29: =MAX(0,O29-P71*0.45-P90) -> 209.25 | Q29: =MAX(0,P29-Q71*0.45-Q90) -> 225.59558 | R29: =MAX(0,Q29-R71*0.45-R90) -> 241.80106 | S29: =MAX(0,R29-S71*0.45-S90) -> 258.87883 | U29: =E29 -> 247 | V29: =I29 -> 188 | W29: =M29 -> 188 | X29: =Q29 -> 225.59558 | Y29: =S29 -> 258.87883
A30: Goodwill | B30: 1155 | C30: 1148 | D30: 1180 | E30: 1137 | F30: 1159 | G30: 1167 | H30: 1128 | I30: 1201 | J30: 1156 | K30: 1074 | L30: 1078 | M30: 1083 | N30: 1099 | O30: 1110 | P30: =O30 -> 1110 | Q30: =P30 -> 1110 | R30: =Q30 -> 1110 | S30: =R30 -> 1110 | U30: =E30 -> 1137 | V30: =I30 -> 1201 | W30: =M30 -> 1083 | X30: =Q30 -> 1110 | Y30: =S30 -> 1110
A31: Intangible assets | B31: 115 | C31: 105 | D31: 98 | E31: 84 | F31: 76 | G31: 68 | H31: 58 | I31: 48 | J31: 43 | K31: 37 | L31: 33 | M31: 41 | N31: 41 | O31: 36 | P31: =MAX(0,O31-P72) -> 31 | Q31: =MAX(0,P31-Q72) -> 25.97059 | R31: =MAX(0,Q31-R72) -> 20.98429 | S31: =MAX(0,R31-S72) -> 15.72959 | U31: =E31 -> 84 | V31: =I31 -> 48 | W31: =M31 -> 41 | X31: =Q31 -> 25.97059 | Y31: =S31 -> 15.72959
A32: Long-term investments | B32: 1134 | C32: 1015 | D32: 903 | E32: 1215 | F32: 1534 | G32: 1931 | H32: 1604 | I32: 1635 | J32: 1958 | K32: 2417 | L32: 2888 | M32: 2181 | N32: 1194 | O32: 1118 | P32: =O32 -> 1118 | Q32: =P32 -> 1118 | R32: =Q32 -> 1118 | S32: =R32 -> 1118 | U32: =E32 -> 1215 | V32: =I32 -> 1635 | W32: =M32 -> 2181 | X32: =Q32 -> 1118 | Y32: =S32 -> 1118
A33: Restricted cash & other non-current assets | B33: 77 | C33: 76 | D33: 75 | E33: 75 | F33: 72 | G33: 70 | H33: 72 | I33: 68 | J33: 65 | K33: 59 | L33: 61 | M33: 61 | N33: 59 | O33: 56 | P33: =O33 -> 56 | Q33: =P33 -> 56 | R33: =Q33 -> 56 | S33: =R33 -> 56 | U33: =E33 -> 75 | V33: =I33 -> 68 | W33: =M33 -> 61 | X33: =Q33 -> 56 | Y33: =S33 -> 56
A34: Finance lease receivables | B34: 0 | C34: 0 | D34: 0 | E34: 0 | F34: 51 | G34: 52 | H34: 64 | I34: 74 | J34: 74 | K34: 68 | L34: 69 | M34: 69 | N34: 71 | O34: 71 | P34: =O34 -> 71 | Q34: =P34 -> 71 | R34: =Q34 -> 71 | S34: =R34 -> 71 | U34: =E34 -> 0 | V34: =I34 -> 74 | W34: =M34 -> 69 | X34: =Q34 -> 71 | Y34: =S34 -> 71
A35: Deferred tax assets | B35: 11 | C35: 15 | D35: 23 | E35: 28 | F35: 41 | G35: 49 | H35: 194 | I35: 186 | J35: 136 | K35: 94 | L35: 87 | M35: 662 | N35: 596 | O35: 563 | P35: =O35 -> 563 | Q35: =P35 -> 563 | R35: =Q35 -> 563 | S35: =R35 -> 563 | U35: =E35 -> 28 | V35: =I35 -> 186 | W35: =M35 -> 662 | X35: =Q35 -> 563 | Y35: =S35 -> 563
A36: Total non-current assets | B36: =SUM(B28:B35) -> 3236 | C36: =SUM(C28:C35) -> 2983 | D36: =SUM(D28:D35) -> 2897 | E36: =SUM(E28:E35) -> 3086 | F36: =SUM(F28:F35) -> 3431 | G36: =SUM(G28:G35) -> 3802 | H36: =SUM(H28:H35) -> 3550 | I36: =SUM(I28:I35) -> 3626 | ... S36: =SUM(S28:S35) -> 3408.7425 | U36: =E36 -> 3086 | V36: =I36 -> 3626 | W36: =M36 -> 4519 | X36: =Q36 -> 3390.0887 | Y36: =S36 -> 3408.7425
A37: Trade & other receivables | B37: 555 | C37: 632 | D37: 747 | E37: 858 | F37: 777 | G37: 753 | H37: 749 | I37: 771 | J37: 749 | K37: 736 | L37: 735 | M37: 802 | N37: 683 | O37: 780 | P37: =P5*Assumptions!B30 -> 815 | Q37: =Q5*Assumptions!C30 -> 819.79383 | R37: =R5*Assumptions!D30 -> 812.7669 | S37: =S5*Assumptions!E30 -> 856.5161 | U37: =E37 -> 858 | V37: =I37 -> 771 | W37: =M37 -> 802 | X37: =Q37 -> 819.79383 | Y37: =S37 -> 856.5161
A38: Income tax receivable | B38: 5 | C38: 8 | D38: 8 | E38: 20 | F38: 21 | G38: 35 | H38: 27 | I38: 28 | J38: 46 | K38: 83 | L38: 117 | M38: 116 | N38: 94 | O38: 92 | P38: =O38 -> 92 | Q38: =P38 -> 92 | R38: =Q38 -> 92 | S38: =R38 -> 92 | U38: =E38 -> 20 | V38: =I38 -> 28 | W38: =M38 -> 116 | X38: =Q38 -> 92 | Y38: =S38 -> 92
A39: Short-term investments | B39: 995 | C39: 866 | D39: 1097 | E39: 1100 | F39: 1220 | G39: 1344 | H39: 1392 | I39: 2667 | J39: 2894 | K39: 3183 | L39: 3606 | M39: 4209 | N39: 3491 | O39: 3450 | P39: =O39 -> 3450 | Q39: =P39 -> 3450 | R39: =Q39 -> 3450 | S39: =R39 -> 3450 | U39: =E39 -> 1100 | V39: =I39 -> 2667 | W39: =M39 -> 4209 | X39: =Q39 -> 3450 | Y39: =S39 -> 3450
A40: Cash & cash equivalents | B40: 2443 | C40: 2550 | D40: 2618 | E40: 3114 | F40: 3451 | G40: 4054 | H40: 4688 | I40: 4781 | J40: 5019 | K40: 5161 | L40: 5456 | M40: 5258 | N40: 5255 | O40: 5938 | P40: =P107 -> 6472.8974 | Q40: =Q107 -> 6886.2698 | R40: =R107 -> 7233.3527 | S40: =S107 -> 7854.0456 | U40: =E40 -> 3114 | V40: =I40 -> 4781 | W40: =M40 -> 5258 | X40: =Q40 -> 6886.2698 | Y40: =S40 -> 7854.0456
A41: Other current assets | B41: 295 | C41: 273 | D41: 225 | E41: 168 | F41: 175 | G41: 158 | H41: 147 | I41: 132 | J41: 146 | K41: 136 | L41: 143 | M41: 111 | N41: 136 | O41: 116 | P41: =P5*Assumptions!B31 -> 125 | Q41: =Q5*Assumptions!C31 -> 125.73525 | R41: =R5*Assumptions!D31 -> 124.6575 | S41: =S5*Assumptions!E31 -> 131.3675 | U41: =E41 -> 168 | V41: =I41 -> 132 | W41: =M41 -> 111 | X41: =Q41 -> 125.73525 | Y41: =S41 -> 131.3675
A42: Total current assets | B42: =SUM(B37:B41) -> 4293 | C42: =SUM(C37:C41) -> 4329 | D42: =SUM(D37:D41) -> 4695 | E42: =SUM(E37:E41) -> 5260 | F42: =SUM(F37:F41) -> 5644 | G42: =SUM(G37:G41) -> 6344 | H42: =SUM(H37:H41) -> 7003 | I42: =SUM(I37:I41) -> 8379 | ... S42: =SUM(S37:S41) -> 12383.929 | U42: =E42 -> 5260 | V42: =I42 -> 8379 | W42: =M42 -> 10496 | X42: =Q42 -> 11373.799 | Y42: =S42 -> 12383.929
A43: Total assets | B43: =B36+B42 -> 7529 | C43: =C36+C42 -> 7312 | D43: =D36+D42 -> 7592 | E43: =E36+E42 -> 8346 | F43: =F36+F42 -> 9075 | G43: =G36+G42 -> 10146 | H43: =H36+H42 -> 10553 | I43: =I36+I42 -> 12005 | ... S43: =S36+S42 -> 15792.672 | U43: =E43 -> 8346 | V43: =I43 -> 12005 | W43: =M43 -> 15015 | X43: =Q43 -> 14763.888 | Y43: =S43 -> 15792.672
A44: Share capital | B44: 0 | C44: 0 | D44: 0 | E44: 0 | F44: 0 | G44: 0 | H44: 0 | I44: 0 | J44: 0 | K44: 0 | L44: 0 | M44: 0 | N44: 0 | O44: 0 | P44: =O44 -> 0 | Q44: =P44 -> 0 | R44: =Q44 -> 0 | S44: =R44 -> 0 | U44: =E44 -> 0 | V44: =I44 -> 0 | W44: =M44 -> 0 | X44: =Q44 -> 0 | Y44: =S44 -> 0
A45: Other paid-in capital | B45: 4864 | C45: 4899 | D45: 4931 | E45: 5155 | F45: 5397 | G45: 5637 | H45: 5825 | I45: 6124 | J45: 6328 | K45: 6420 | L45: 6459 | M45: 6496 | N45: 6560 | O45: 6624 | P45: =O45+P97 -> 6654 | Q45: =P45+Q97 -> 6684 | R45: =Q45+R97 -> 6714 | S45: =R45+S97 -> 6744 | U45: =E45 -> 5155 | V45: =I45 -> 6124 | W45: =M45 -> 6496 | X45: =Q45 -> 6684 | Y45: =S45 -> 6744
A46: Treasury shares | B46: -262 | C46: -262 | D46: -262 | E46: -262 | F46: -262 | G46: -262 | H46: -262 | I46: -262 | J46: -262 | K46: -262 | L46: -328 | M46: -701 | N46: -1007 | O46: -1248 | P46: =O46+P98 -> -1548 | Q46: =P46+Q98 -> -1848 | R46: =Q46+R98 -> -2148 | S46: =R46+S98 -> -2448 | U46: =E46 -> -262 | V46: =I46 -> -262 | W46: =M46 -> -701 | X46: =Q46 -> -1848 | Y46: =S46 -> -2448
A47: Other reserves | B47: 1615 | C47: 1594 | D47: 1582 | E47: 1812 | F47: 2159 | G47: 2595 | H47: 2481 | I47: 2707 | J47: 3000 | K47: 3374 | L47: 3654 | M47: 3366 | N47: 2581 | O47: 2588 | P47: =P43-P64-P44-P45-P46-P48 -> 2627.08 | Q47: =Q43-Q64-Q44-Q45-Q46-Q48 -> 2664.2047 | R47: =R43-R64-R44-R45-R46-R48 -> 2700.9239 | S47: =S43-S64-S44-S45-S46-S48 -> 2739.1874 | U47: =E47 -> 1812 | V47: =I47 -> 2707 | W47: =M47 -> 3366 | X47: =Q47 -> 2664.2047 | Y47: =S47 -> 2739.1874
A48: Accumulated deficit / retained earnings | B48: -3875 | C48: -4177 | D48: -4112 | E48: -4182 | F48: -3985 | G48: -3711 | H48: -3411 | I48: -3044 | J48: -2819 | K48: -2905 | L48: -2006 | M48: -832 | N48: -124 | O48: 421 | P48: =O48+P20 -> 975.5302 | Q48: =P48+Q20 -> 1582.3802 | R48: =Q48+R20 -> 2187.3431 | S48: =R48+S20 -> 2815.4907 | U48: =E48 -> -4182 | V48: =I48 -> -3044 | W48: =M48 -> -832 | X48: =Q48 -> 1582.3802 | Y48: =S48 -> 2815.4907
A49: Total equity | B49: =SUM(B44:B48) -> 2342 | C49: =SUM(C44:C48) -> 2054 | D49: =SUM(D44:D48) -> 2139 | E49: =SUM(E44:E48) -> 2523 | F49: =SUM(F44:F48) -> 3309 | G49: =SUM(G44:G48) -> 4259 | H49: =SUM(H44:H48) -> 4633 | I49: =SUM(I44:I48) -> 5525 | ... S49: =SUM(S44:S48) -> 9850.6781 | U49: =E49 -> 2523 | V49: =I49 -> 5525 | W49: =M49 -> 8329 | X49: =Q49 -> 9082.5849 | Y49: =S49 -> 9850.6781
A50: Non-current exchangeable notes | B50: 1156 | C50: 1167 | D50: 1209 | E50: 1203 | F50: 1270 | G50: 1323 | H50: 1340 | I50: 1539 | J50: 0 | K50: 0 | L50: 0 | M50: 0 | N50: 0 | O50: 0 | P50: 0 | Q50: 0 | R50: 0 | S50: 0 | U50: =E50 -> 1203 | V50: =I50 -> 1539 | W50: =M50 -> 0 | X50: =Q50 -> 0 | Y50: =S50 -> 0
A51: Non-current lease liabilities | B51: 546 | C51: 522 | D51: 520 | E51: 493 | F51: 493 | G51: 472 | H51: 446 | I51: 462 | J51: 448 | K51: 453 | L51: 444 | M51: 433 | N51: 414 | O51: 404 | P51: =O51*(1+Assumptions!B35) -> 395.92 | Q51: =P51*(1+Assumptions!C35) -> 388.0016 | R51: =Q51*(1+Assumptions!D35) -> 380.24157 | S51: =R51*(1+Assumptions!E35) -> 372.63674 | U51: =E51 -> 493 | V51: =I51 -> 462 | W51: =M51 -> 433 | X51: =Q51 -> 388.0016 | Y51: =S51 -> 372.63674
A52: Non-current accrued & other liabilities | B52: 17 | C52: 14 | D52: 14 | E52: 26 | F52: 17 | G52: 11 | H52: 5 | I52: 5 | J52: 4 | K52: 4 | L52: 1 | M52: 2 | N52: 2 | O52: 2 | P52: =O52 -> 2 | Q52: =P52 -> 2 | R52: =Q52 -> 2 | S52: =R52 -> 2 | U52: =E52 -> 26 | V52: =I52 -> 5 | W52: =M52 -> 2 | X52: =Q52 -> 2 | Y52: =S52 -> 2
A53: Non-current provisions | B53: 3 | C53: 3 | D53: 3 | E53: 3 | F53: 3 | G53: 3 | H53: 3 | I53: 3 | J53: 2 | K53: 3 | L53: 3 | M53: 3 | N53: 3 | O53: 13 | P53: =O53 -> 13 | Q53: =P53 -> 13 | R53: =Q53 -> 13 | S53: =R53 -> 13 | U53: =E53 -> 3 | V53: =I53 -> 3 | W53: =M53 -> 3 | X53: =Q53 -> 13 | Y53: =S53 -> 13
A54: Deferred tax liabilities | B54: 6 | C54: 6 | D54: 6 | E54: 8 | F54: 17 | G54: 19 | H54: 20 | I54: 21 | J54: 21 | K54: 66 | L54: 223 | M54: 163 | N54: 11 | O54: 30 | P54: =O54 -> 30 | Q54: =P54 -> 30 | R54: =Q54 -> 30 | S54: =R54 -> 30 | U54: =E54 -> 8 | V54: =I54 -> 21 | W54: =M54 -> 163 | X54: =Q54 -> 30 | Y54: =S54 -> 30
A55: Total non-current liabilities | B55: =SUM(B50:B54) -> 1728 | C55: =SUM(C50:C54) -> 1712 | D55: =SUM(D50:D54) -> 1752 | E55: =SUM(E50:E54) -> 1733 | F55: =SUM(F50:F54) -> 1800 | G55: =SUM(G50:G54) -> 1828 | H55: =SUM(H50:H54) -> 1814 | I55: =SUM(I50:I54) -> 2030 | ... S55: =SUM(S50:S54) -> 417.63674 | U55: =E55 -> 1733 | V55: =I55 -> 2030 | W55: =M55 -> 601 | X55: =Q55 -> 433.0016 | Y55: =S55 -> 417.63674
A56: Trade & other payables | B56: 850 | C56: 893 | D56: 945 | E56: 978 | F56: 1048 | G56: 1091 | H56: 1084 | I56: 1342 | J56: 1064 | K56: 1171 | L56: 1193 | M56: 1194 | N56: 1250 | O56: 1325 | P56: =P6*Assumptions!B32 -> 1409.1 | Q56: =Q6*Assumptions!C32 -> 1421.613 | R56: =R6*Assumptions!D32 -> 1407.3333 | S56: =S6*Assumptions!E32 -> 1480.8796 | U56: =E56 -> 978 | V56: =I56 -> 1342 | W56: =M56 -> 1194 | X56: =Q56 -> 1421.613 | Y56: =S56 -> 1480.8796
A57: Income tax payable | B57: 9 | C57: 11 | D57: 8 | E57: 12 | F57: 14 | G57: 17 | H57: 21 | I57: 33 | J57: 40 | K57: 42 | L57: 31 | M57: 72 | N57: 150 | O57: 171 | P57: =MAX(0,O57+P19+P86) -> 197.26722 | Q57: =MAX(0,P57+Q19+Q86) -> 226.01275 | R57: =MAX(0,Q57+R19+R86) -> 254.66888 | S57: =MAX(0,R57+S19+S86) -> 284.42324 | U57: =E57 -> 12 | V57: =I57 -> 33 | W57: =M57 -> 72 | X57: =Q57 -> 226.01275 | Y57: =S57 -> 284.42324
A58: Deferred revenue | B58: 524 | C58: 536 | D58: 599 | E58: 622 | F58: 634 | G58: 657 | H58: 680 | I58: 683 | J58: 675 | K58: 665 | L58: 692 | M58: 711 | N58: 750 | O58: 778 | P58: =P5*Assumptions!B33 -> 815 | Q58: =Q5*Assumptions!C33 -> 819.79383 | R58: =R5*Assumptions!D33 -> 812.7669 | S58: =S5*Assumptions!E33 -> 856.5161 | U58: =E58 -> 622 | V58: =I58 -> 683 | W58: =M58 -> 711 | X58: =Q58 -> 819.79383 | Y58: =S58 -> 856.5161
A59: Current accrued & other liabilities | B59: 2025 | C59: 2053 | D59: 2108 | E59: 2440 | F59: 2228 | G59: 2223 | H59: 2275 | I59: 2347 | J59: 2471 | K59: 2442 | L59: 2519 | M59: 2589 | N59: 2471 | O59: 2573 | P59: =P5*Assumptions!B34 -> 2700 | Q59: =Q5*Assumptions!C34 -> 2715.8814 | R59: =R5*Assumptions!D34 -> 2692.602 | S59: =S5*Assumptions!E34 -> 2837.538 | U59: =E59 -> 2440 | V59: =I59 -> 2347 | W59: =M59 -> 2589 | X59: =Q59 -> 2715.8814 | Y59: =S59 -> 2837.538
A60: Current exchangeable notes | B60: 0 | C60: 0 | D60: 0 | E60: 0 | F60: 0 | G60: 0 | H60: 0 | I60: 0 | J60: 1654 | K60: 1929 | L60: 1741 | M60: 1458 | N60: 0 | O60: 0 | P60: 0 | Q60: 0 | R60: 0 | S60: 0 | U60: =E60 -> 0 | V60: =I60 -> 0 | W60: =M60 -> 1458 | X60: =Q60 -> 0 | Y60: =S60 -> 0
A61: Current provisions | B61: 27 | C61: 25 | D61: 24 | E61: 21 | F61: 20 | G61: 24 | H61: 24 | I61: 25 | J61: 39 | K61: 47 | L61: 50 | M61: 51 | N61: 49 | O61: 45 | P61: =Assumptions!B36 -> 45 | Q61: =Assumptions!C36 -> 45 | R61: =Assumptions!D36 -> 45 | S61: =Assumptions!E36 -> 45 | U61: =E61 -> 21 | V61: =I61 -> 25 | W61: =M61 -> 51 | X61: =Q61 -> 45 | Y61: =S61 -> 45
A62: Derivative liabilities | B62: 24 | C62: 28 | D62: 17 | E62: 17 | F62: 22 | G62: 47 | H62: 22 | I62: 20 | J62: 22 | K62: 16 | L62: 13 | M62: 10 | N62: 18 | O62: 22 | P62: =Assumptions!B37 -> 20 | Q62: =Assumptions!C37 -> 20 | R62: =Assumptions!D37 -> 20 | S62: =Assumptions!E37 -> 20 | U62: =E62 -> 17 | V62: =I62 -> 20 | W62: =M62 -> 10 | X62: =Q62 -> 20 | Y62: =S62 -> 20
A63: Total current liabilities | B63: =SUM(B56:B62) -> 3459 | C63: =SUM(C56:C62) -> 3546 | D63: =SUM(D56:D62) -> 3701 | E63: =SUM(E56:E62) -> 4090 | F63: =SUM(F56:F62) -> 3966 | G63: =SUM(G56:G62) -> 4059 | H63: =SUM(H56:H62) -> 4106 | I63: =SUM(I56:I62) -> 4450 | ... S63: =SUM(S56:S62) -> 5524.3569 | U63: =E63 -> 4090 | V63: =I63 -> 4450 | W63: =M63 -> 6085 | X63: =Q63 -> 5248.301 | Y63: =S63 -> 5524.3569
A64: Total liabilities | B64: =B55+B63 -> 5187 | C64: =C55+C63 -> 5258 | D64: =D55+D63 -> 5453 | E64: =E55+E63 -> 5823 | F64: =F55+F63 -> 5766 | G64: =G55+G63 -> 5887 | H64: =H55+H63 -> 5920 | I64: =I55+I63 -> 6480 | ... S64: =S55+S63 -> 5941.9936 | U64: =E64 -> 5823 | V64: =I64 -> 6480 | W64: =M64 -> 6686 | X64: =Q64 -> 5681.3026 | Y64: =S64 -> 5941.9936
A65: Total equity & liabilities | B65: =B49+B64 -> 7529 | C65: =C49+C64 -> 7312 | D65: =D49+D64 -> 7592 | E65: =E49+E64 -> 8346 | F65: =F49+F64 -> 9075 | G65: =G49+G64 -> 10146 | H65: =H49+H64 -> 10553 | I65: =I49+I64 -> 12005 | ... S65: =S49+S64 -> 15792.672 | U65: =E65 -> 8346 | V65: =I65 -> 12005 | W65: =M65 -> 15015 | X65: =Q65 -> 14763.888 | Y65: =S65 -> 15792.672
A66: Balance sheet check | B66: =B43-B65 -> 0 | C66: =C43-C65 -> 0 | D66: =D43-D65 -> 0 | E66: =E43-E65 -> 0 | F66: =F43-F65 -> 0 | G66: =G43-G65 -> 0 | H66: =H43-H65 -> 0 | I66: =I43-I65 -> 0 | ... S66: =S43-S65 -> 0 | U66: =E66 -> 0 | V66: =I66 -> 0 | W66: =M66 -> 0 | X66: =Q66 -> 0 | Y66: =S66 -> 0
A69: Cash Flow Statement
A70: Net income/(loss) | B70: ='Raw Numbers'!$B$27 -> -225 | C70: ='Raw Numbers'!$C$27-'Raw Numbers'!$B$27 -> -302 | D70: ='Raw Numbers'!$D$27-'Raw Numbers'!$C$27 -> 65 | E70: ='Raw Numbers'!$E$27-'Raw Numbers'!$D$27 -> -70 | F70: ='Raw Numbers'!$F$27 -> 197 | G70: ='Raw Numbers'!$G$27-'Raw Numbers'!$F$27 -> 274 | H70: ='Raw Numbers'!$H$27-'Raw Numbers'!$G$27 -> 300 | I70: ='Raw Numbers'!$I$27-'Raw Numbers'!$H$27 -> 367 | J70: ='Raw Numbers'!$J$27 -> 225 | K70: ='Raw Numbers'!$K$27-'Raw Numbers'!$J$27 -> -86 | L70: ='Raw Numbers'!$L$27-'Raw Numbers'!$K$27 -> 899 | M70: ='Raw Numbers'!$M$27-'Raw Numbers'!$L$27 -> 1174 | N70: ='Raw Numbers'!$N$27 -> 721 | O70: ='Raw Numbers'!$O$27-'Raw Numbers'!$N$27 -> 545 | P70: =P20 -> 554.5302 | Q70: =Q20 -> 606.85002 | R70: =R20 -> 604.9629 | S70: =S20 -> 628.14759 | U70: =SUM(B70,C70,D70,E70) -> -532 | V70: =SUM(F70,G70,H70,I70) -> 1138 | W70: =SUM(J70,K70,L70,M70) -> 2212 | X70: =SUM(N70,O70,P70,Q70) -> 2427.3802 | Y70: =SUM(P70,Q70,R70,S70) -> 2394.4907
A71: Depreciation - PP&E and ROU assets | B71: ='Raw Numbers'!$B$28 -> 31 | C71: ='Raw Numbers'!$C$28-'Raw Numbers'!$B$28 -> 30 | D71: ='Raw Numbers'!$D$28-'Raw Numbers'!$C$28 -> 26 | E71: ='Raw Numbers'!$E$28-'Raw Numbers'!$D$28 -> 23 | F71: ='Raw Numbers'!$F$28 -> 22 | G71: ='Raw Numbers'!$G$28-'Raw Numbers'!$F$28 -> 21 | H71: ='Raw Numbers'!$H$28-'Raw Numbers'!$G$28 -> 21 | I71: ='Raw Numbers'!$I$28-'Raw Numbers'!$H$28 -> 21 | J71: ='Raw Numbers'!$J$28 -> 20 | K71: ='Raw Numbers'!$K$28-'Raw Numbers'!$J$28 -> 20 | L71: ='Raw Numbers'!$L$28-'Raw Numbers'!$K$28 -> 19 | M71: ='Raw Numbers'!$M$28-'Raw Numbers'!$L$28 -> 20 | N71: ='Raw Numbers'!$N$28 -> 20 | O71: ='Raw Numbers'!$O$28-'Raw Numbers'!$N$28 -> 24 | P71: =P5*Assumptions!B19 -> 25 | Q71: =Q5*Assumptions!C19 -> 25.14705 | R71: =R5*Assumptions!D19 -> 24.9315 | S71: =S5*Assumptions!E19 -> 26.2735 | U71: =SUM(B71,C71,D71,E71) -> 110 | V71: =SUM(F71,G71,H71,I71) -> 85 | W71: =SUM(J71,K71,L71,M71) -> 79 | X71: =SUM(N71,O71,P71,Q71) -> 94.14705 | Y71: =SUM(P71,Q71,R71,S71) -> 101.35205
A72: Amortization of intangible assets | B72: ='Raw Numbers'!$B$29 -> 13 | C72: ='Raw Numbers'!$C$29-'Raw Numbers'!$B$29 -> 14 | D72: ='Raw Numbers'!$D$29-'Raw Numbers'!$C$29 -> 10 | E72: ='Raw Numbers'!$E$29-'Raw Numbers'!$D$29 -> 11 | F72: ='Raw Numbers'!$F$29 -> 9 | G72: ='Raw Numbers'!$G$29-'Raw Numbers'!$F$29 -> 9 | H72: ='Raw Numbers'!$H$29-'Raw Numbers'!$G$29 -> 9 | I72: ='Raw Numbers'!$I$29-'Raw Numbers'!$H$29 -> 9 | J72: ='Raw Numbers'!$J$29 -> 7 | K72: ='Raw Numbers'!$K$29-'Raw Numbers'!$J$29 -> 6 | L72: ='Raw Numbers'!$L$29-'Raw Numbers'!$K$29 -> 5 | M72: ='Raw Numbers'!$M$29-'Raw Numbers'!$L$29 -> 5 | N72: ='Raw Numbers'!$N$29 -> 6 | O72: ='Raw Numbers'!$O$29-'Raw Numbers'!$N$29 -> 5 | P72: =P5*Assumptions!B20 -> 5 | Q72: =Q5*Assumptions!C20 -> 5.02941 | R72: =R5*Assumptions!D20 -> 4.9863 | S72: =S5*Assumptions!E20 -> 5.2547 | U72: =SUM(B72,C72,D72,E72) -> 48 | V72: =SUM(F72,G72,H72,I72) -> 36 | W72: =SUM(J72,K72,L72,M72) -> 23 | X72: =SUM(N72,O72,P72,Q72) -> 21.02941 | Y72: =SUM(P72,Q72,R72,S72) -> 20.27041
A73: Impairment of real estate assets | B73: ='Raw Numbers'!$B$30 -> 0 | C73: ='Raw Numbers'!$C$30-'Raw Numbers'!$B$30 -> 90 | D73: ='Raw Numbers'!$D$30-'Raw Numbers'!$C$30 -> 0 | E73: ='Raw Numbers'!$E$30-'Raw Numbers'!$D$30 -> 33 | F73: ='Raw Numbers'!$F$30 -> 4 | G73: ='Raw Numbers'!$G$30-'Raw Numbers'!$F$30 -> 14 | H73: ='Raw Numbers'!$H$30-'Raw Numbers'!$G$30 -> 0 | I73: ='Raw Numbers'!$I$30-'Raw Numbers'!$H$30 -> 25 | J73: ='Raw Numbers'!$J$30 -> 2 | K73: ='Raw Numbers'!$K$30-'Raw Numbers'!$J$30 -> 1 | L73: ='Raw Numbers'!$L$30-'Raw Numbers'!$K$30 -> 5 | M73: ='Raw Numbers'!$M$30-'Raw Numbers'!$L$30 -> 0 | N73: ='Raw Numbers'!$N$30 -> 4 | O73: ='Raw Numbers'!$O$30-'Raw Numbers'!$N$30 -> 0 | P73: 0 | Q73: 0 | R73: 0 | S73: 0 | U73: =SUM(B73,C73,D73,E73) -> 123 | V73: =SUM(F73,G73,H73,I73) -> 43 | W73: =SUM(J73,K73,L73,M73) -> 8 | X73: =SUM(N73,O73,P73,Q73) -> 4 | Y73: =SUM(P73,Q73,R73,S73) -> 0
A74: Write-off of content assets | B74: ='Raw Numbers'!$B$31 -> 0 | C74: ='Raw Numbers'!$C$31-'Raw Numbers'!$B$31 -> 30 | D74: ='Raw Numbers'!$D$31-'Raw Numbers'!$C$31 -> 0 | E74: ='Raw Numbers'!$E$31-'Raw Numbers'!$D$31 -> -1 | F74: ='Raw Numbers'!$F$31 -> 0 | G74: ='Raw Numbers'!$G$31-'Raw Numbers'!$F$31 -> 0 | H74: ='Raw Numbers'!$H$31-'Raw Numbers'!$G$31 -> 0 | I74: ='Raw Numbers'!$I$31-'Raw Numbers'!$H$31 -> 0 | J74: ='Raw Numbers'!$J$31 -> 0 | K74: ='Raw Numbers'!$K$31-'Raw Numbers'!$J$31 -> 0 | L74: ='Raw Numbers'!$L$31-'Raw Numbers'!$K$31 -> 0 | M74: ='Raw Numbers'!$M$31-'Raw Numbers'!$L$31 -> 0 | N74: ='Raw Numbers'!$N$31 -> 0 | O74: ='Raw Numbers'!$O$31-'Raw Numbers'!$N$31 -> 0 | P74: 0 | Q74: 0 | R74: 0 | S74: 0 | U74: =SUM(B74,C74,D74,E74) -> 29 | V74: =SUM(F74,G74,H74,I74) -> 0 | W74: =SUM(J74,K74,L74,M74) -> 0 | X74: =SUM(N74,O74,P74,Q74) -> 0 | Y74: =SUM(P74,Q74,R74,S74) -> 0
A75: Share-based compensation expense | B75: ='Raw Numbers'!$B$32 -> 105 | C75: ='Raw Numbers'!$C$32-'Raw Numbers'!$B$32 -> 97 | D75: ='Raw Numbers'!$D$32-'Raw Numbers'!$C$32 -> 85 | E75: ='Raw Numbers'!$E$32-'Raw Numbers'!$D$32 -> 34 | F75: ='Raw Numbers'!$F$32 -> 69 | G75: ='Raw Numbers'!$G$32-'Raw Numbers'!$F$32 -> 81 | H75: ='Raw Numbers'!$H$32-'Raw Numbers'!$G$32 -> 63 | I75: ='Raw Numbers'!$I$32-'Raw Numbers'!$H$32 -> 54 | J75: ='Raw Numbers'!$J$32 -> 42 | K75: ='Raw Numbers'!$K$32-'Raw Numbers'!$J$32 -> 73 | L75: ='Raw Numbers'!$L$32-'Raw Numbers'!$K$32 -> 75 | M75: ='Raw Numbers'!$M$32-'Raw Numbers'!$L$32 -> 57 | N75: ='Raw Numbers'!$N$32 -> 56 | O75: ='Raw Numbers'!$O$32-'Raw Numbers'!$N$32 -> 86 | P75: =P5*Assumptions!B21 -> 80 | Q75: =Q5*Assumptions!C21 -> 80.47056 | R75: =R5*Assumptions!D21 -> 79.7808 | S75: =S5*Assumptions!E21 -> 84.0752 | U75: =SUM(B75,C75,D75,E75) -> 321 | V75: =SUM(F75,G75,H75,I75) -> 267 | W75: =SUM(J75,K75,L75,M75) -> 247 | X75: =SUM(N75,O75,P75,Q75) -> 302.47056 | Y75: =SUM(P75,Q75,R75,S75) -> 324.32656
A76: Finance income | B76: ='Raw Numbers'!$B$33 -> -27 | C76: ='Raw Numbers'!$C$33-'Raw Numbers'!$B$33 -> -33 | D76: ='Raw Numbers'!$D$33-'Raw Numbers'!$C$33 -> -55 | E76: ='Raw Numbers'!$E$33-'Raw Numbers'!$D$33 -> -46 | F76: ='Raw Numbers'!$F$33 -> -59 | G76: ='Raw Numbers'!$G$33-'Raw Numbers'!$F$33 -> -76 | H76: ='Raw Numbers'!$H$33-'Raw Numbers'!$G$33 -> -66 | I76: ='Raw Numbers'!$I$33-'Raw Numbers'!$H$33 -> -127 | J76: ='Raw Numbers'!$J$33 -> -71 | K76: ='Raw Numbers'!$K$33-'Raw Numbers'!$J$33 -> -89 | L76: ='Raw Numbers'!$L$33-'Raw Numbers'!$K$33 -> -262 | M76: ='Raw Numbers'!$M$33-'Raw Numbers'!$L$33 -> 130 | N76: ='Raw Numbers'!$N$33 -> -248 | O76: ='Raw Numbers'!$O$33-'Raw Numbers'!$N$33 -> -86 | P76: =-P15 -> -82.145 | Q76: =-Q15 -> -86.825352 | R76: =-R15 -> -90.442361 | S76: =-S15 -> -93.479336 | U76: =SUM(B76,C76,D76,E76) -> -161 | V76: =SUM(F76,G76,H76,I76) -> -328 | W76: =SUM(J76,K76,L76,M76) -> -292 | X76: =SUM(N76,O76,P76,Q76) -> -502.97035 | Y76: =SUM(P76,Q76,R76,S76) -> -352.89205
A77: Finance costs | B77: ='Raw Numbers'!$B$34 -> 77 | C77: ='Raw Numbers'!$C$34-'Raw Numbers'!$B$34 -> 27 | D77: ='Raw Numbers'!$D$34-'Raw Numbers'!$C$34 -> 14 | E77: ='Raw Numbers'!$E$34-'Raw Numbers'!$D$34 -> 102 | F77: ='Raw Numbers'!$F$34 -> 53 | G77: ='Raw Numbers'!$G$34-'Raw Numbers'!$F$34 -> 72 | H77: ='Raw Numbers'!$H$34-'Raw Numbers'!$G$34 -> 122 | I77: ='Raw Numbers'!$I$34-'Raw Numbers'!$H$34 -> 105 | J77: ='Raw Numbers'!$J$34 -> 252 | K77: ='Raw Numbers'!$K$34-'Raw Numbers'!$J$34 -> 447 | L77: ='Raw Numbers'!$L$34-'Raw Numbers'!$K$34 -> 17 | M77: ='Raw Numbers'!$M$34-'Raw Numbers'!$L$34 -> -450 | N77: ='Raw Numbers'!$N$34 -> 26 | O77: ='Raw Numbers'!$O$34-'Raw Numbers'!$N$34 -> 21 | P77: =-P16 -> 22.5 | Q77: =-Q16 -> 22.632345 | R77: =-R16 -> 22.43835 | S77: =-S16 -> 23.64615 | U77: =SUM(B77,C77,D77,E77) -> 220 | V77: =SUM(F77,G77,H77,I77) -> 352 | W77: =SUM(J77,K77,L77,M77) -> 266 | X77: =SUM(N77,O77,P77,Q77) -> 92.132345 | Y77: =SUM(P77,Q77,R77,S77) -> 91.216845
A78: Income tax expense/(benefit) | B78: ='Raw Numbers'!$B$35 -> 19 | C78: ='Raw Numbers'!$C$35-'Raw Numbers'!$B$35 -> 61 | D78: ='Raw Numbers'!$D$35-'Raw Numbers'!$C$35 -> 8 | E78: ='Raw Numbers'!$E$35-'Raw Numbers'!$D$35 -> -61 | F78: ='Raw Numbers'!$F$35 -> -23 | G78: ='Raw Numbers'!$G$35-'Raw Numbers'!$F$35 -> -4 | H78: ='Raw Numbers'!$H$35-'Raw Numbers'!$G$35 -> 98 | I78: ='Raw Numbers'!$I$35-'Raw Numbers'!$H$35 -> 132 | J78: ='Raw Numbers'!$J$35 -> 103 | K78: ='Raw Numbers'!$K$35-'Raw Numbers'!$J$35 -> 134 | L78: ='Raw Numbers'!$L$35-'Raw Numbers'!$K$35 -> -72 | M78: ='Raw Numbers'!$M$35-'Raw Numbers'!$L$35 -> -153 | N78: ='Raw Numbers'!$N$35 -> 216 | O78: ='Raw Numbers'!$O$35-'Raw Numbers'!$N$35 -> 175 | P78: =P19 -> 175.1148 | Q78: =Q19 -> 191.63685 | R78: =R19 -> 191.04091 | S78: =S19 -> 198.3624 | U78: =SUM(B78,C78,D78,E78) -> 27 | V78: =SUM(F78,G78,H78,I78) -> 203 | W78: =SUM(J78,K78,L78,M78) -> 12 | X78: =SUM(N78,O78,P78,Q78) -> 757.75165 | Y78: =SUM(P78,Q78,R78,S78) -> 756.15496
A79: Other non-cash items | B79: ='Raw Numbers'!$B$36 -> -5 | C79: ='Raw Numbers'!$C$36-'Raw Numbers'!$B$36 -> 2 | D79: ='Raw Numbers'!$D$36-'Raw Numbers'!$C$36 -> -1 | E79: ='Raw Numbers'!$E$36-'Raw Numbers'!$D$36 -> 5 | F79: ='Raw Numbers'!$F$36 -> 0 | G79: ='Raw Numbers'!$G$36-'Raw Numbers'!$F$36 -> -1 | H79: ='Raw Numbers'!$H$36-'Raw Numbers'!$G$36 -> 0 | I79: ='Raw Numbers'!$I$36-'Raw Numbers'!$H$36 -> 3 | J79: ='Raw Numbers'!$J$36 -> 0 | K79: ='Raw Numbers'!$K$36-'Raw Numbers'!$J$36 -> 8 | L79: ='Raw Numbers'!$L$36-'Raw Numbers'!$K$36 -> 1 | M79: ='Raw Numbers'!$M$36-'Raw Numbers'!$L$36 -> 1 | N79: ='Raw Numbers'!$N$36 -> -2 | O79: ='Raw Numbers'!$O$36-'Raw Numbers'!$N$36 -> 1 | P79: 0 | Q79: 0 | R79: 0 | S79: 0 | U79: =SUM(B79,C79,D79,E79) -> 1 | V79: =SUM(F79,G79,H79,I79) -> 2 | W79: =SUM(J79,K79,L79,M79) -> 10 | X79: =SUM(N79,O79,P79,Q79) -> -1 | Y79: =SUM(P79,Q79,R79,S79) -> 0
A80: Change in trade receivables & other assets | B80: ='Raw Numbers'!$B$37 -> 118 | C80: ='Raw Numbers'!$C$37-'Raw Numbers'!$B$37 -> -97 | D80: ='Raw Numbers'!$D$37-'Raw Numbers'!$C$37 -> -69 | E80: ='Raw Numbers'!$E$37-'Raw Numbers'!$D$37 -> -97 | F80: ='Raw Numbers'!$F$37 -> 80 | G80: ='Raw Numbers'!$G$37-'Raw Numbers'!$F$37 -> 40 | H80: ='Raw Numbers'!$H$37-'Raw Numbers'!$G$37 -> -4 | I80: ='Raw Numbers'!$I$37-'Raw Numbers'!$H$37 -> 29 | J80: ='Raw Numbers'!$J$37 -> -4 | K80: ='Raw Numbers'!$K$37-'Raw Numbers'!$J$37 -> -19 | L80: ='Raw Numbers'!$L$37-'Raw Numbers'!$K$37 -> -26 | M80: ='Raw Numbers'!$M$37-'Raw Numbers'!$L$37 -> -66 | N80: ='Raw Numbers'!$N$37 -> 91 | O80: ='Raw Numbers'!$O$37-'Raw Numbers'!$N$37 -> -80 | P80: =-((P37+P38+P41)-(O37+O38+O41)) -> -44 | Q80: =-((Q37+Q38+Q41)-(P37+P38+P41)) -> -5.52908 | R80: =-((R37+R38+R41)-(Q37+Q38+Q41)) -> 8.10468 | S80: =-((S37+S38+S41)-(R37+R38+R41)) -> -50.4592 | U80: =SUM(B80,C80,D80,E80) -> -145 | V80: =SUM(F80,G80,H80,I80) -> 145 | W80: =SUM(J80,K80,L80,M80) -> -115 | X80: =SUM(N80,O80,P80,Q80) -> -38.52908 | Y80: =SUM(P80,Q80,R80,S80) -> -91.8836
A81: Change in trade & other liabilities | B81: ='Raw Numbers'!$B$38 -> -57 | C81: ='Raw Numbers'!$C$38-'Raw Numbers'!$B$38 -> 77 | D81: ='Raw Numbers'!$D$38-'Raw Numbers'!$C$38 -> 62 | E81: ='Raw Numbers'!$E$38-'Raw Numbers'!$D$38 -> 419 | F81: ='Raw Numbers'!$F$38 -> -171 | G81: ='Raw Numbers'!$G$38-'Raw Numbers'!$F$38 -> 28 | H81: ='Raw Numbers'!$H$38-'Raw Numbers'!$G$38 -> 86 | I81: ='Raw Numbers'!$I$38-'Raw Numbers'!$H$38 -> 240 | J81: ='Raw Numbers'!$J$38 -> -90 | K81: ='Raw Numbers'!$K$38-'Raw Numbers'!$J$38 -> 201 | L81: ='Raw Numbers'!$L$38-'Raw Numbers'!$K$38 -> 100 | M81: ='Raw Numbers'!$M$38-'Raw Numbers'!$L$38 -> 70 | N81: ='Raw Numbers'!$N$38 -> -94 | O81: ='Raw Numbers'!$O$38-'Raw Numbers'!$N$38 -> 150 | P81: =(P56+P59+P52)-(O56+O59+O52) -> 211.1 | Q81: =(Q56+Q59+Q52)-(P56+P59+P52) -> 28.394431 | R81: =(R56+R59+R52)-(Q56+Q59+Q52) -> -37.559119 | S81: =(S56+S59+S52)-(R56+R59+R52) -> 218.48224 | U81: =SUM(B81,C81,D81,E81) -> 501 | V81: =SUM(F81,G81,H81,I81) -> 183 | W81: =SUM(J81,K81,L81,M81) -> 281 | X81: =SUM(N81,O81,P81,Q81) -> 295.49443 | Y81: =SUM(P81,Q81,R81,S81) -> 420.41755
A82: Change in deferred revenue | B82: ='Raw Numbers'!$B$39 -> 6 | C82: ='Raw Numbers'!$C$39-'Raw Numbers'!$B$39 -> 18 | D82: ='Raw Numbers'!$D$39-'Raw Numbers'!$C$39 -> 56 | E82: ='Raw Numbers'!$E$39-'Raw Numbers'!$D$39 -> 33 | F82: ='Raw Numbers'!$F$39 -> 7 | G82: ='Raw Numbers'!$G$39-'Raw Numbers'!$F$39 -> 21 | H82: ='Raw Numbers'!$H$39-'Raw Numbers'!$G$39 -> 33 | I82: ='Raw Numbers'!$I$39-'Raw Numbers'!$H$39 -> -16 | J82: ='Raw Numbers'!$J$39 -> 3 | K82: ='Raw Numbers'!$K$39-'Raw Numbers'!$J$39 -> 12 | L82: ='Raw Numbers'!$L$39-'Raw Numbers'!$K$39 -> 25 | M82: ='Raw Numbers'!$M$39-'Raw Numbers'!$L$39 -> 20 | N82: ='Raw Numbers'!$N$39 -> 35 | O82: ='Raw Numbers'!$O$39-'Raw Numbers'!$N$39 -> 25 | P82: =P58-O58 -> 37 | Q82: =Q58-P58 -> 4.79383 | R82: =R58-Q58 -> -7.02693 | S82: =S58-R58 -> 43.7492 | U82: =SUM(B82,C82,D82,E82) -> 113 | V82: =SUM(F82,G82,H82,I82) -> 45 | W82: =SUM(J82,K82,L82,M82) -> 60 | X82: =SUM(N82,O82,P82,Q82) -> 101.79383 | Y82: =SUM(P82,Q82,R82,S82) -> 78.5161
A83: Change in provisions | B83: ='Raw Numbers'!$B$40 -> 1 | C83: ='Raw Numbers'!$C$40-'Raw Numbers'!$B$40 -> -2 | D83: ='Raw Numbers'!$D$40-'Raw Numbers'!$C$40 -> -2 | E83: ='Raw Numbers'!$E$40-'Raw Numbers'!$D$40 -> -2 | F83: ='Raw Numbers'!$F$40 -> 0 | G83: ='Raw Numbers'!$G$40-'Raw Numbers'!$F$40 -> 4 | H83: ='Raw Numbers'!$H$40-'Raw Numbers'!$G$40 -> 0 | I83: ='Raw Numbers'!$I$40-'Raw Numbers'!$H$40 -> -1 | J83: ='Raw Numbers'!$J$40 -> 12 | K83: ='Raw Numbers'!$K$40-'Raw Numbers'!$J$40 -> 8 | L83: ='Raw Numbers'!$L$40-'Raw Numbers'!$K$40 -> 2 | M83: ='Raw Numbers'!$M$40-'Raw Numbers'!$L$40 -> 0 | N83: ='Raw Numbers'!$N$40 -> -3 | O83: ='Raw Numbers'!$O$40-'Raw Numbers'!$N$40 -> -6 | P83: =(P61+P53)-(O61+O53) -> 0 | Q83: =(Q61+Q53)-(P61+P53) -> 0 | R83: =(R61+R53)-(Q61+Q53) -> 0 | S83: =(S61+S53)-(R61+R53) -> 0 | U83: =SUM(B83,C83,D83,E83) -> -5 | V83: =SUM(F83,G83,H83,I83) -> 3 | W83: =SUM(J83,K83,L83,M83) -> 22 | X83: =SUM(N83,O83,P83,Q83) -> -9 | Y83: =SUM(P83,Q83,R83,S83) -> 0
A84: Interest paid | B84: ='Raw Numbers'!$B$41 -> -10 | C84: ='Raw Numbers'!$C$41-'Raw Numbers'!$B$41 -> -10 | D84: ='Raw Numbers'!$D$41-'Raw Numbers'!$C$41 -> -9 | E84: ='Raw Numbers'!$E$41-'Raw Numbers'!$D$41 -> -9 | F84: ='Raw Numbers'!$F$41 -> -9 | G84: ='Raw Numbers'!$G$41-'Raw Numbers'!$F$41 -> -9 | H84: ='Raw Numbers'!$H$41-'Raw Numbers'!$G$41 -> -9 | I84: ='Raw Numbers'!$I$41-'Raw Numbers'!$H$41 -> -9 | J84: ='Raw Numbers'!$J$41 -> -13 | K84: ='Raw Numbers'!$K$41-'Raw Numbers'!$J$41 -> -6 | L84: ='Raw Numbers'!$L$41-'Raw Numbers'!$K$41 -> -11 | M84: ='Raw Numbers'!$M$41-'Raw Numbers'!$L$41 -> -6 | N84: ='Raw Numbers'!$N$41 -> -8 | O84: ='Raw Numbers'!$O$41-'Raw Numbers'!$N$41 -> -7 | P84: =P16 -> -22.5 | Q84: =Q16 -> -22.632345 | R84: =R16 -> -22.43835 | S84: =S16 -> -23.64615 | U84: =SUM(B84,C84,D84,E84) -> -38 | V84: =SUM(F84,G84,H84,I84) -> -36 | W84: =SUM(J84,K84,L84,M84) -> -36 | X84: =SUM(N84,O84,P84,Q84) -> -60.132345 | Y84: =SUM(P84,Q84,R84,S84) -> -91.216845
A85: Interest received | B85: ='Raw Numbers'!$B$42 -> 23 | C85: ='Raw Numbers'!$C$42-'Raw Numbers'!$B$42 -> 26 | D85: ='Raw Numbers'!$D$42-'Raw Numbers'!$C$42 -> 28 | E85: ='Raw Numbers'!$E$42-'Raw Numbers'!$D$42 -> 34 | F85: ='Raw Numbers'!$F$42 -> 37 | G85: ='Raw Numbers'!$G$42-'Raw Numbers'!$F$42 -> 41 | H85: ='Raw Numbers'!$H$42-'Raw Numbers'!$G$42 -> 77 | I85: ='Raw Numbers'!$I$42-'Raw Numbers'!$H$42 -> 61 | J85: ='Raw Numbers'!$J$42 -> 70 | K85: ='Raw Numbers'!$K$42-'Raw Numbers'!$J$42 -> 57 | L85: ='Raw Numbers'!$L$42-'Raw Numbers'!$K$42 -> 57 | M85: ='Raw Numbers'!$M$42-'Raw Numbers'!$L$42 -> 58 | N85: ='Raw Numbers'!$N$42 -> 52 | O85: ='Raw Numbers'!$O$42-'Raw Numbers'!$N$42 -> 48 | P85: =P15 -> 82.145 | Q85: =Q15 -> 86.825352 | R85: =R15 -> 90.442361 | S85: =S15 -> 93.479336 | U85: =SUM(B85,C85,D85,E85) -> 111 | V85: =SUM(F85,G85,H85,I85) -> 216 | W85: =SUM(J85,K85,L85,M85) -> 242 | X85: =SUM(N85,O85,P85,Q85) -> 268.97035 | Y85: =SUM(P85,Q85,R85,S85) -> 352.89205
A86: Income taxes paid | B86: ='Raw Numbers'!$B$43 -> -10 | C86: ='Raw Numbers'!$C$43-'Raw Numbers'!$B$43 -> -15 | D86: ='Raw Numbers'!$D$43-'Raw Numbers'!$C$43 -> -7 | E86: ='Raw Numbers'!$E$43-'Raw Numbers'!$D$43 -> -11 | F86: ='Raw Numbers'!$F$43 -> -5 | G86: ='Raw Numbers'!$G$43-'Raw Numbers'!$F$43 -> -23 | H86: ='Raw Numbers'!$H$43-'Raw Numbers'!$G$43 -> -15 | I86: ='Raw Numbers'!$I$43-'Raw Numbers'!$H$43 -> -10 | J86: ='Raw Numbers'!$J$43 -> -19 | K86: ='Raw Numbers'!$K$43-'Raw Numbers'!$J$43 -> -58 | L86: ='Raw Numbers'!$L$43-'Raw Numbers'!$K$43 -> -5 | M86: ='Raw Numbers'!$M$43-'Raw Numbers'!$L$43 -> -4 | N86: ='Raw Numbers'!$N$43 -> -36 | O86: ='Raw Numbers'!$O$43-'Raw Numbers'!$N$43 -> -85 | P86: =-P19*Assumptions!B22 -> -148.84758 | Q86: =-Q19*Assumptions!C22 -> -162.89132 | R86: =-R19*Assumptions!D22 -> -162.38478 | S86: =-S19*Assumptions!E22 -> -168.60804 | U86: =SUM(B86,C86,D86,E86) -> -43 | V86: =SUM(F86,G86,H86,I86) -> -53 | W86: =SUM(J86,K86,L86,M86) -> -86 | X86: =SUM(N86,O86,P86,Q86) -> -432.7389 | Y86: =SUM(P86,Q86,R86,S86) -> -642.73172
A87: Net cash flows from operating activities | B87: ='Raw Numbers'!$B$44 -> 59 | C87: ='Raw Numbers'!$C$44-'Raw Numbers'!$B$44 -> 13 | D87: ='Raw Numbers'!$D$44-'Raw Numbers'!$C$44 -> 211 | E87: ='Raw Numbers'!$E$44-'Raw Numbers'!$D$44 -> 397 | F87: ='Raw Numbers'!$F$44 -> 211 | G87: ='Raw Numbers'!$G$44-'Raw Numbers'!$F$44 -> 492 | H87: ='Raw Numbers'!$H$44-'Raw Numbers'!$G$44 -> 715 | I87: ='Raw Numbers'!$I$44-'Raw Numbers'!$H$44 -> 883 | J87: ='Raw Numbers'!$J$44 -> 539 | K87: ='Raw Numbers'!$K$44-'Raw Numbers'!$J$44 -> 709 | L87: ='Raw Numbers'!$L$44-'Raw Numbers'!$K$44 -> 829 | M87: ='Raw Numbers'!$M$44-'Raw Numbers'!$L$44 -> 856 | N87: ='Raw Numbers'!$N$44 -> 836 | O87: ='Raw Numbers'!$O$44-'Raw Numbers'!$N$44 -> 816 | P87: =SUM(P70:P86) -> 894.89742 | Q87: =SUM(Q70:Q86) -> 773.90175 | R87: =SUM(R70:R86) -> 706.83626 | S87: =SUM(S70:S86) -> 985.27759 | U87: =SUM(B87,C87,D87,E87) -> 680 | V87: =SUM(F87,G87,H87,I87) -> 2301 | W87: =SUM(J87,K87,L87,M87) -> 2933 | X87: =SUM(N87,O87,P87,Q87) -> 3320.7992 | Y87: =SUM(P87,Q87,R87,S87) -> 3360.913
A88: Business combinations | B88: ='Raw Numbers'!$B$45 -> 0 | C88: ='Raw Numbers'!$C$45-'Raw Numbers'!$B$45 -> 0 | D88: ='Raw Numbers'!$D$45-'Raw Numbers'!$C$45 -> 0 | E88: ='Raw Numbers'!$E$45-'Raw Numbers'!$D$45 -> 0 | F88: ='Raw Numbers'!$F$45 -> 0 | G88: ='Raw Numbers'!$G$45-'Raw Numbers'!$F$45 -> 0 | H88: ='Raw Numbers'!$H$45-'Raw Numbers'!$G$45 -> 0 | I88: ='Raw Numbers'!$I$45-'Raw Numbers'!$H$45 -> 0 | J88: ='Raw Numbers'!$J$45 -> 0 | K88: ='Raw Numbers'!$K$45-'Raw Numbers'!$J$45 -> 0 | L88: ='Raw Numbers'!$L$45-'Raw Numbers'!$K$45 -> 0 | M88: ='Raw Numbers'!$M$45-'Raw Numbers'!$L$45 -> -9 | N88: ='Raw Numbers'!$N$45 -> 0 | O88: ='Raw Numbers'!$O$45-'Raw Numbers'!$N$45 -> 0 | P88: 0 | Q88: 0 | R88: 0 | S88: 0 | U88: =SUM(B88,C88,D88,E88) -> 0 | V88: =SUM(F88,G88,H88,I88) -> 0 | W88: =SUM(J88,K88,L88,M88) -> -9 | X88: =SUM(N88,O88,P88,Q88) -> 0 | Y88: =SUM(P88,Q88,R88,S88) -> 0
A89: Deferred consideration | B89: ='Raw Numbers'!$B$46 -> -7 | C89: ='Raw Numbers'!$C$46-'Raw Numbers'!$B$46 -> 0 | D89: ='Raw Numbers'!$D$46-'Raw Numbers'!$C$46 -> 0 | E89: ='Raw Numbers'!$E$46-'Raw Numbers'!$D$46 -> 0 | F89: ='Raw Numbers'!$F$46 -> -7 | G89: ='Raw Numbers'!$G$46-'Raw Numbers'!$F$46 -> -3 | H89: ='Raw Numbers'!$H$46-'Raw Numbers'!$G$46 -> 0 | I89: ='Raw Numbers'!$I$46-'Raw Numbers'!$H$46 -> 0 | J89: ='Raw Numbers'!$J$46 -> -7 | K89: ='Raw Numbers'!$K$46-'Raw Numbers'!$J$46 -> -2 | L89: ='Raw Numbers'!$L$46-'Raw Numbers'!$K$46 -> 0 | M89: ='Raw Numbers'!$M$46-'Raw Numbers'!$L$46 -> 0 | N89: ='Raw Numbers'!$N$46 -> 0 | O89: ='Raw Numbers'!$O$46-'Raw Numbers'!$N$46 -> 0 | P89: 0 | Q89: 0 | R89: 0 | S89: 0 | U89: =SUM(B89,C89,D89,E89) -> -7 | V89: =SUM(F89,G89,H89,I89) -> -10 | W89: =SUM(J89,K89,L89,M89) -> -9 | X89: =SUM(N89,O89,P89,Q89) -> 0 | Y89: =SUM(P89,Q89,R89,S89) -> 0
A90: Purchases of property & equipment | B90: ='Raw Numbers'!$B$47 -> -2 | C90: ='Raw Numbers'!$C$47-'Raw Numbers'!$B$47 -> -2 | D90: ='Raw Numbers'!$D$47-'Raw Numbers'!$C$47 -> -1 | E90: ='Raw Numbers'!$E$47-'Raw Numbers'!$D$47 -> -1 | F90: ='Raw Numbers'!$F$47 -> -5 | G90: ='Raw Numbers'!$G$47-'Raw Numbers'!$F$47 -> -2 | H90: ='Raw Numbers'!$H$47-'Raw Numbers'!$G$47 -> -4 | I90: ='Raw Numbers'!$I$47-'Raw Numbers'!$H$47 -> -6 | J90: ='Raw Numbers'!$J$47 -> -6 | K90: ='Raw Numbers'!$K$47-'Raw Numbers'!$J$47 -> -10 | L90: ='Raw Numbers'!$L$47-'Raw Numbers'!$K$47 -> -23 | M90: ='Raw Numbers'!$M$47-'Raw Numbers'!$L$47 -> -22 | N90: ='Raw Numbers'!$N$47 -> -5 | O90: ='Raw Numbers'!$O$47-'Raw Numbers'!$N$47 -> -20 | P90: =-P5*Assumptions!B23 -> -27.5 | Q90: =-Q5*Assumptions!C23 -> -27.661755 | R90: =-R5*Assumptions!D23 -> -27.42465 | S90: =-S5*Assumptions!E23 -> -28.90085 | U90: =SUM(B90,C90,D90,E90) -> -6 | V90: =SUM(F90,G90,H90,I90) -> -17 | W90: =SUM(J90,K90,L90,M90) -> -61 | X90: =SUM(N90,O90,P90,Q90) -> -80.161755 | Y90: =SUM(P90,Q90,R90,S90) -> -111.48726
A91: Purchases of short-term investments | B91: ='Raw Numbers'!$B$48 -> -237 | C91: ='Raw Numbers'!$C$48-'Raw Numbers'!$B$48 -> -138 | D91: ='Raw Numbers'!$D$48-'Raw Numbers'!$C$48 -> -406 | E91: ='Raw Numbers'!$E$48-'Raw Numbers'!$D$48 -> -809 | F91: ='Raw Numbers'!$F$48 -> -998 | G91: ='Raw Numbers'!$G$48-'Raw Numbers'!$F$48 -> -1285 | H91: ='Raw Numbers'!$H$48-'Raw Numbers'!$G$48 -> -1439 | I91: ='Raw Numbers'!$I$48-'Raw Numbers'!$H$48 -> -3553 | J91: ='Raw Numbers'!$J$48 -> -3929 | K91: ='Raw Numbers'!$K$48-'Raw Numbers'!$J$48 -> -4643 | L91: ='Raw Numbers'!$L$48-'Raw Numbers'!$K$48 -> -4783 | M91: ='Raw Numbers'!$M$48-'Raw Numbers'!$L$48 -> -5916 | N91: ='Raw Numbers'!$N$48 -> -6740 | O91: ='Raw Numbers'!$O$48-'Raw Numbers'!$N$48 -> -7301 | P91: 0 | Q91: 0 | R91: 0 | S91: 0 | U91: =SUM(B91,C91,D91,E91) -> -1590 | V91: =SUM(F91,G91,H91,I91) -> -7275 | W91: =SUM(J91,K91,L91,M91) -> -19271 | X91: =SUM(N91,O91,P91,Q91) -> -14041 | Y91: =SUM(P91,Q91,R91,S91) -> 0
A92: Sales & maturities of short-term investments | B92: ='Raw Numbers'!$B$49 -> 111 | C92: ='Raw Numbers'!$C$49-'Raw Numbers'!$B$49 -> 265 | D92: ='Raw Numbers'!$D$49-'Raw Numbers'!$C$49 -> 201 | E92: ='Raw Numbers'!$E$49-'Raw Numbers'!$D$49 -> 802 | F92: ='Raw Numbers'!$F$49 -> 900 | G92: ='Raw Numbers'!$G$49-'Raw Numbers'!$F$49 -> 1179 | H92: ='Raw Numbers'!$H$49-'Raw Numbers'!$G$49 -> 1364 | I92: ='Raw Numbers'!$I$49-'Raw Numbers'!$H$49 -> 2361 | J92: ='Raw Numbers'!$J$49 -> 3630 | K92: ='Raw Numbers'!$K$49-'Raw Numbers'!$J$49 -> 4228 | L92: ='Raw Numbers'!$L$49-'Raw Numbers'!$K$49 -> 4369 | M92: ='Raw Numbers'!$M$49-'Raw Numbers'!$L$49 -> 5318 | N92: ='Raw Numbers'!$N$49 -> 7484 | O92: ='Raw Numbers'!$O$49-'Raw Numbers'!$N$49 -> 7351 | P92: 0 | Q92: 0 | R92: 0 | S92: 0 | U92: =SUM(B92,C92,D92,E92) -> 1379 | V92: =SUM(F92,G92,H92,I92) -> 5804 | W92: =SUM(J92,K92,L92,M92) -> 17545 | X92: =SUM(N92,O92,P92,Q92) -> 14835 | Y92: =SUM(P92,Q92,R92,S92) -> 0
A93: Change in restricted cash | B93: ='Raw Numbers'!$B$50 -> 0 | C93: ='Raw Numbers'!$C$50-'Raw Numbers'!$B$50 -> -2 | D93: ='Raw Numbers'!$D$50-'Raw Numbers'!$C$50 -> 6 | E93: ='Raw Numbers'!$E$50-'Raw Numbers'!$D$50 -> 0 | F93: ='Raw Numbers'!$F$50 -> 1 | G93: ='Raw Numbers'!$G$50-'Raw Numbers'!$F$50 -> 0 | H93: ='Raw Numbers'!$H$50-'Raw Numbers'!$G$50 -> 0 | I93: ='Raw Numbers'!$I$50-'Raw Numbers'!$H$50 -> 0 | J93: ='Raw Numbers'!$J$50 -> 1 | K93: ='Raw Numbers'!$K$50-'Raw Numbers'!$J$50 -> 1 | L93: ='Raw Numbers'!$L$50-'Raw Numbers'!$K$50 -> 0 | M93: ='Raw Numbers'!$M$50-'Raw Numbers'!$L$50 -> 0 | N93: ='Raw Numbers'!$N$50 -> 1 | O93: ='Raw Numbers'!$O$50-'Raw Numbers'!$N$50 -> 2 | P93: 0 | Q93: 0 | R93: 0 | S93: 0 | U93: =SUM(B93,C93,D93,E93) -> 4 | V93: =SUM(F93,G93,H93,I93) -> 1 | W93: =SUM(J93,K93,L93,M93) -> 2 | X93: =SUM(N93,O93,P93,Q93) -> 3 | Y93: =SUM(P93,Q93,R93,S93) -> 0
A94: Dividends received | B94: ='Raw Numbers'!$B$51 -> 0 | C94: ='Raw Numbers'!$C$51-'Raw Numbers'!$B$51 -> 0 | D94: ='Raw Numbers'!$D$51-'Raw Numbers'!$C$51 -> 0 | E94: ='Raw Numbers'!$E$51-'Raw Numbers'!$D$51 -> 0 | F94: ='Raw Numbers'!$F$51 -> 0 | G94: ='Raw Numbers'!$G$51-'Raw Numbers'!$F$51 -> 18 | H94: ='Raw Numbers'!$H$51-'Raw Numbers'!$G$51 -> 0 | I94: ='Raw Numbers'!$I$51-'Raw Numbers'!$H$51 -> 1 | J94: ='Raw Numbers'!$J$51 -> 0 | K94: ='Raw Numbers'!$K$51-'Raw Numbers'!$J$51 -> 22 | L94: ='Raw Numbers'!$L$51-'Raw Numbers'!$K$51 -> 1 | M94: ='Raw Numbers'!$M$51-'Raw Numbers'!$L$51 -> 0 | N94: ='Raw Numbers'!$N$51 -> 0 | O94: ='Raw Numbers'!$O$51-'Raw Numbers'!$N$51 -> 29 | P94: 0 | Q94: 0 | R94: 0 | S94: 0 | U94: =SUM(B94,C94,D94,E94) -> 0 | V94: =SUM(F94,G94,H94,I94) -> 19 | W94: =SUM(J94,K94,L94,M94) -> 23 | X94: =SUM(N94,O94,P94,Q94) -> 29 | Y94: =SUM(P94,Q94,R94,S94) -> 0
A95: Other investing activities | B95: ='Raw Numbers'!$B$52 -> 13 | C95: ='Raw Numbers'!$C$52-'Raw Numbers'!$B$52 -> -10 | D95: ='Raw Numbers'!$D$52-'Raw Numbers'!$C$52 -> -3 | E95: ='Raw Numbers'!$E$52-'Raw Numbers'!$D$52 -> 3 | F95: ='Raw Numbers'!$F$52 -> -5 | G95: ='Raw Numbers'!$G$52-'Raw Numbers'!$F$52 -> 1 | H95: ='Raw Numbers'!$H$52-'Raw Numbers'!$G$52 -> -3 | I95: ='Raw Numbers'!$I$52-'Raw Numbers'!$H$52 -> -1 | J95: ='Raw Numbers'!$J$52 -> -3 | K95: ='Raw Numbers'!$K$52-'Raw Numbers'!$J$52 -> 0 | L95: ='Raw Numbers'!$L$52-'Raw Numbers'!$K$52 -> -2 | M95: ='Raw Numbers'!$M$52-'Raw Numbers'!$L$52 -> 0 | N95: ='Raw Numbers'!$N$52 -> -8 | O95: ='Raw Numbers'!$O$52-'Raw Numbers'!$N$52 -> 1 | P95: 0 | Q95: 0 | R95: 0 | S95: 0 | U95: =SUM(B95,C95,D95,E95) -> 3 | V95: =SUM(F95,G95,H95,I95) -> -8 | W95: =SUM(J95,K95,L95,M95) -> -5 | X95: =SUM(N95,O95,P95,Q95) -> -7 | Y95: =SUM(P95,Q95,R95,S95) -> 0
A96: Net cash flows from/(used in) investing activities | B96: ='Raw Numbers'!$B$53 -> -122 | C96: ='Raw Numbers'!$C$53-'Raw Numbers'!$B$53 -> 113 | D96: ='Raw Numbers'!$D$53-'Raw Numbers'!$C$53 -> -203 | E96: ='Raw Numbers'!$E$53-'Raw Numbers'!$D$53 -> -5 | F96: ='Raw Numbers'!$F$53 -> -114 | G96: ='Raw Numbers'!$G$53-'Raw Numbers'!$F$53 -> -92 | H96: ='Raw Numbers'!$H$53-'Raw Numbers'!$G$53 -> -82 | I96: ='Raw Numbers'!$I$53-'Raw Numbers'!$H$53 -> -1198 | J96: ='Raw Numbers'!$J$53 -> -314 | K96: ='Raw Numbers'!$K$53-'Raw Numbers'!$J$53 -> -404 | L96: ='Raw Numbers'!$L$53-'Raw Numbers'!$K$53 -> -438 | M96: ='Raw Numbers'!$M$53-'Raw Numbers'!$L$53 -> -629 | N96: ='Raw Numbers'!$N$53 -> 732 | O96: ='Raw Numbers'!$O$53-'Raw Numbers'!$N$53 -> 62 | P96: =SUM(P88:P95) -> -27.5 | Q96: =SUM(Q88:Q95) -> -27.661755 | R96: =SUM(R88:R95) -> -27.42465 | S96: =SUM(S88:S95) -> -28.90085 | U96: =SUM(B96,C96,D96,E96) -> -217 | V96: =SUM(F96,G96,H96,I96) -> -1486 | W96: =SUM(J96,K96,L96,M96) -> -1785 | X96: =SUM(N96,O96,P96,Q96) -> 738.83825 | Y96: =SUM(P96,Q96,R96,S96) -> -111.48726
A97: Proceeds from exercise of share options | B97: ='Raw Numbers'!$B$54 -> 75 | C97: ='Raw Numbers'!$C$54-'Raw Numbers'!$B$54 -> 35 | D97: ='Raw Numbers'!$D$54-'Raw Numbers'!$C$54 -> 32 | E97: ='Raw Numbers'!$E$54-'Raw Numbers'!$D$54 -> 224 | F97: ='Raw Numbers'!$F$54 -> 242 | G97: ='Raw Numbers'!$G$54-'Raw Numbers'!$F$54 -> 240 | H97: ='Raw Numbers'!$H$54-'Raw Numbers'!$G$54 -> 152 | I97: ='Raw Numbers'!$I$54-'Raw Numbers'!$H$54 -> 299 | J97: ='Raw Numbers'!$J$54 -> 204 | K97: ='Raw Numbers'!$K$54-'Raw Numbers'!$J$54 -> 92 | L97: ='Raw Numbers'!$L$54-'Raw Numbers'!$K$54 -> 39 | M97: ='Raw Numbers'!$M$54-'Raw Numbers'!$L$54 -> 37 | N97: ='Raw Numbers'!$N$54 -> 64 | O97: ='Raw Numbers'!$O$54-'Raw Numbers'!$N$54 -> 64 | P97: =Assumptions!B24 -> 30 | Q97: =Assumptions!C24 -> 30 | R97: =Assumptions!D24 -> 30 | S97: =Assumptions!E24 -> 30 | U97: =SUM(B97,C97,D97,E97) -> 366 | V97: =SUM(F97,G97,H97,I97) -> 933 | W97: =SUM(J97,K97,L97,M97) -> 372 | X97: =SUM(N97,O97,P97,Q97) -> 188 | Y97: =SUM(P97,Q97,R97,S97) -> 120
A98: Repurchases of ordinary shares | B98: ='Raw Numbers'!$B$55 -> 0 | C98: ='Raw Numbers'!$C$55-'Raw Numbers'!$B$55 -> 0 | D98: ='Raw Numbers'!$D$55-'Raw Numbers'!$C$55 -> 0 | E98: ='Raw Numbers'!$E$55-'Raw Numbers'!$D$55 -> 0 | F98: ='Raw Numbers'!$F$55 -> 0 | G98: ='Raw Numbers'!$G$55-'Raw Numbers'!$F$55 -> 0 | H98: ='Raw Numbers'!$H$55-'Raw Numbers'!$G$55 -> 0 | I98: ='Raw Numbers'!$I$55-'Raw Numbers'!$H$55 -> 0 | J98: ='Raw Numbers'!$J$55 -> 0 | K98: ='Raw Numbers'!$K$55-'Raw Numbers'!$J$55 -> 0 | L98: ='Raw Numbers'!$L$55-'Raw Numbers'!$K$55 -> -58 | M98: ='Raw Numbers'!$M$55-'Raw Numbers'!$L$55 -> -381 | N98: ='Raw Numbers'!$N$55 -> -306 | O98: ='Raw Numbers'!$O$55-'Raw Numbers'!$N$55 -> -232 | P98: =-Assumptions!B25 -> -300 | Q98: =-Assumptions!C25 -> -300 | R98: =-Assumptions!D25 -> -300 | S98: =-Assumptions!E25 -> -300 | U98: =SUM(B98,C98,D98,E98) -> 0 | V98: =SUM(F98,G98,H98,I98) -> 0 | W98: =SUM(J98,K98,L98,M98) -> -439 | X98: =SUM(N98,O98,P98,Q98) -> -1138 | Y98: =SUM(P98,Q98,R98,S98) -> -1200
A99: Lease payments | B99: ='Raw Numbers'!$B$56 -> -15 | C99: ='Raw Numbers'!$C$56-'Raw Numbers'!$B$56 -> -27 | D99: ='Raw Numbers'!$D$56-'Raw Numbers'!$C$56 -> -13 | E99: ='Raw Numbers'!$E$56-'Raw Numbers'!$D$56 -> -11 | F99: ='Raw Numbers'!$F$56 -> -15 | G99: ='Raw Numbers'!$G$56-'Raw Numbers'!$F$56 -> -24 | H99: ='Raw Numbers'!$H$56-'Raw Numbers'!$G$56 -> -18 | I99: ='Raw Numbers'!$I$56-'Raw Numbers'!$H$56 -> -12 | J99: ='Raw Numbers'!$J$56 -> -22 | K99: ='Raw Numbers'!$K$56-'Raw Numbers'!$J$56 -> -22 | L99: ='Raw Numbers'!$L$56-'Raw Numbers'!$K$56 -> -15 | M99: ='Raw Numbers'!$M$56-'Raw Numbers'!$L$56 -> -14 | N99: ='Raw Numbers'!$N$56 -> -20 | O99: ='Raw Numbers'!$O$56-'Raw Numbers'!$N$56 -> -16 | P99: =-P5*Assumptions!B26 -> -22.5 | Q99: =-Q5*Assumptions!C26 -> -22.632345 | R99: =-R5*Assumptions!D26 -> -22.43835 | S99: =-S5*Assumptions!E26 -> -23.64615 | U99: =SUM(B99,C99,D99,E99) -> -66 | V99: =SUM(F99,G99,H99,I99) -> -69 | W99: =SUM(J99,K99,L99,M99) -> -73 | X99: =SUM(N99,O99,P99,Q99) -> -81.132345 | Y99: =SUM(P99,Q99,R99,S99) -> -91.216845
A100: Lease incentives received | B100: ='Raw Numbers'!$B$57 -> 2 | C100: ='Raw Numbers'!$C$57-'Raw Numbers'!$B$57 -> 0 | D100: ='Raw Numbers'!$D$57-'Raw Numbers'!$C$57 -> 0 | E100: ='Raw Numbers'!$E$57-'Raw Numbers'!$D$57 -> 0 | F100: ='Raw Numbers'!$F$57 -> 0 | G100: ='Raw Numbers'!$G$57-'Raw Numbers'!$F$57 -> 0 | H100: ='Raw Numbers'!$H$57-'Raw Numbers'!$G$57 -> 0 | I100: ='Raw Numbers'!$I$57-'Raw Numbers'!$H$57 -> 0 | J100: ='Raw Numbers'!$J$57 -> 0 | K100: ='Raw Numbers'!$K$57-'Raw Numbers'!$J$57 -> 0 | L100: ='Raw Numbers'!$L$57-'Raw Numbers'!$K$57 -> 0 | M100: ='Raw Numbers'!$M$57-'Raw Numbers'!$L$57 -> 0 | N100: ='Raw Numbers'!$N$57 -> 0 | O100: ='Raw Numbers'!$O$57-'Raw Numbers'!$N$57 -> 0 | P100: 0 | Q100: 0 | R100: 0 | S100: 0 | U100: =SUM(B100,C100,D100,E100) -> 2 | V100: =SUM(F100,G100,H100,I100) -> 0 | W100: =SUM(J100,K100,L100,M100) -> 0 | X100: =SUM(N100,O100,P100,Q100) -> 0 | Y100: =SUM(P100,Q100,R100,S100) -> 0
A101: Repayment of exchangeable notes | B101: ='Raw Numbers'!$B$58 -> 0 | C101: ='Raw Numbers'!$C$58-'Raw Numbers'!$B$58 -> 0 | D101: ='Raw Numbers'!$D$58-'Raw Numbers'!$C$58 -> 0 | E101: ='Raw Numbers'!$E$58-'Raw Numbers'!$D$58 -> 0 | F101: ='Raw Numbers'!$F$58 -> 0 | G101: ='Raw Numbers'!$G$58-'Raw Numbers'!$F$58 -> 0 | H101: ='Raw Numbers'!$H$58-'Raw Numbers'!$G$58 -> 0 | I101: ='Raw Numbers'!$I$58-'Raw Numbers'!$H$58 -> 0 | J101: ='Raw Numbers'!$J$58 -> 0 | K101: ='Raw Numbers'!$K$58-'Raw Numbers'!$J$58 -> 0 | L101: ='Raw Numbers'!$L$58-'Raw Numbers'!$K$58 -> 0 | M101: ='Raw Numbers'!$M$58-'Raw Numbers'!$L$58 -> 0 | N101: ='Raw Numbers'!$N$58 -> -1304 | O101: ='Raw Numbers'!$O$58-'Raw Numbers'!$N$58 -> 0 | P101: 0 | Q101: 0 | R101: 0 | S101: 0 | U101: =SUM(B101,C101,D101,E101) -> 0 | V101: =SUM(F101,G101,H101,I101) -> 0 | W101: =SUM(J101,K101,L101,M101) -> 0 | X101: =SUM(N101,O101,P101,Q101) -> -1304 | Y101: =SUM(P101,Q101,R101,S101) -> 0
A102: Employee tax withholding on equity awards | B102: ='Raw Numbers'!$B$59 -> -13 | C102: ='Raw Numbers'!$C$59-'Raw Numbers'!$B$59 -> -16 | D102: ='Raw Numbers'!$D$59-'Raw Numbers'!$C$59 -> -20 | E102: ='Raw Numbers'!$E$59-'Raw Numbers'!$D$59 -> -19 | F102: ='Raw Numbers'!$F$59 -> -25 | G102: ='Raw Numbers'!$G$59-'Raw Numbers'!$F$59 -> -32 | H102: ='Raw Numbers'!$H$59-'Raw Numbers'!$G$59 -> -35 | I102: ='Raw Numbers'!$I$59-'Raw Numbers'!$H$59 -> -43 | J102: ='Raw Numbers'!$J$59 -> -56 | K102: ='Raw Numbers'!$K$59-'Raw Numbers'!$J$59 -> -59 | L102: ='Raw Numbers'!$L$59-'Raw Numbers'!$K$59 -> -66 | M102: ='Raw Numbers'!$M$59-'Raw Numbers'!$L$59 -> -60 | N102: ='Raw Numbers'!$N$59 -> -45 | O102: ='Raw Numbers'!$O$59-'Raw Numbers'!$N$59 -> -34 | P102: =-P5*Assumptions!B27 -> -40 | Q102: =-Q5*Assumptions!C27 -> -40.23528 | R102: =-R5*Assumptions!D27 -> -39.8904 | S102: =-S5*Assumptions!E27 -> -42.0376 | U102: =SUM(B102,C102,D102,E102) -> -68 | V102: =SUM(F102,G102,H102,I102) -> -135 | W102: =SUM(J102,K102,L102,M102) -> -241 | X102: =SUM(N102,O102,P102,Q102) -> -159.23528 | Y102: =SUM(P102,Q102,R102,S102) -> -162.16328
A103: Net cash flows from/(used in) financing activities | B103: ='Raw Numbers'!$B$60 -> 49 | C103: ='Raw Numbers'!$C$60-'Raw Numbers'!$B$60 -> -8 | D103: ='Raw Numbers'!$D$60-'Raw Numbers'!$C$60 -> -1 | E103: ='Raw Numbers'!$E$60-'Raw Numbers'!$D$60 -> 194 | F103: ='Raw Numbers'!$F$60 -> 202 | G103: ='Raw Numbers'!$G$60-'Raw Numbers'!$F$60 -> 184 | H103: ='Raw Numbers'!$H$60-'Raw Numbers'!$G$60 -> 99 | I103: ='Raw Numbers'!$I$60-'Raw Numbers'!$H$60 -> 244 | J103: ='Raw Numbers'!$J$60 -> 126 | K103: ='Raw Numbers'!$K$60-'Raw Numbers'!$J$60 -> 11 | L103: ='Raw Numbers'!$L$60-'Raw Numbers'!$K$60 -> -100 | M103: ='Raw Numbers'!$M$60-'Raw Numbers'!$L$60 -> -418 | N103: ='Raw Numbers'!$N$60 -> -1611 | O103: ='Raw Numbers'!$O$60-'Raw Numbers'!$N$60 -> -218 | P103: =SUM(P97:P102) -> -332.5 | Q103: =SUM(Q97:Q102) -> -332.86762 | R103: =SUM(R97:R102) -> -332.32875 | S103: =SUM(S97:S102) -> -335.68375 | U103: =SUM(B103,C103,D103,E103) -> 234 | V103: =SUM(F103,G103,H103,I103) -> 729 | W103: =SUM(J103,K103,L103,M103) -> -381 | X103: =SUM(N103,O103,P103,Q103) -> -2494.3676 | Y103: =SUM(P103,Q103,R103,S103) -> -1333.3801
A104: Net increase/(decrease) in cash | B104: ='Raw Numbers'!$B$61 -> -14 | C104: ='Raw Numbers'!$C$61-'Raw Numbers'!$B$61 -> 118 | D104: ='Raw Numbers'!$D$61-'Raw Numbers'!$C$61 -> 7 | E104: ='Raw Numbers'!$E$61-'Raw Numbers'!$D$61 -> 586 | F104: ='Raw Numbers'!$F$61 -> 299 | G104: ='Raw Numbers'!$G$61-'Raw Numbers'!$F$61 -> 584 | H104: ='Raw Numbers'!$H$61-'Raw Numbers'!$G$61 -> 732 | I104: ='Raw Numbers'!$I$61-'Raw Numbers'!$H$61 -> -71 | J104: ='Raw Numbers'!$J$61 -> 351 | K104: ='Raw Numbers'!$K$61-'Raw Numbers'!$J$61 -> 316 | L104: ='Raw Numbers'!$L$61-'Raw Numbers'!$K$61 -> 291 | M104: ='Raw Numbers'!$M$61-'Raw Numbers'!$L$61 -> -191 | N104: ='Raw Numbers'!$N$61 -> -43 | O104: ='Raw Numbers'!$O$61-'Raw Numbers'!$N$61 -> 660 | P104: =P87+P96+P103 -> 534.89742 | Q104: =Q87+Q96+Q103 -> 413.37237 | R104: =R87+R96+R103 -> 347.08286 | S104: =S87+S96+S103 -> 620.69299 | U104: =SUM(B104,C104,D104,E104) -> 697 | V104: =SUM(F104,G104,H104,I104) -> 1544 | W104: =SUM(J104,K104,L104,M104) -> 767 | X104: =SUM(N104,O104,P104,Q104) -> 1565.2698 | Y104: =SUM(P104,Q104,R104,S104) -> 1916.0456
A105: Cash & cash equivalents at beginning of period | B105: ='Raw Numbers'!$B$62 -> 2483 | C105: =B107 -> 2443 | D105: =C107 -> 2550 | E105: =D107 -> 2615 | F105: ='Raw Numbers'!$F$62 -> 3114 | G105: =F107 -> 3451 | H105: =G107 -> 4054 | I105: =H107 -> 4688 | J105: ='Raw Numbers'!$J$62 -> 4781 | K105: =J107 -> 5019 | L105: =K107 -> 5161 | M105: =L107 -> 5456 | N105: ='Raw Numbers'!$N$62 -> 5258 | O105: =N107 -> 5255 | P105: =O107 -> 5938 | Q105: =P107 -> 6472.8974 | R105: =Q107 -> 6886.2698 | S105: =R107 -> 7233.3527 | U105: =B105 -> 2483 | V105: =F105 -> 3114 | W105: =J105 -> 4781 | X105: =N105 -> 5258 | Y105: =P105 -> 5938
...

Sheet Trading Comps
A1: Spotify Trading Comps & Multiple Reclassification
A3: Valuation Date | B3: Current SPOT Price ($) | C3: EUR / USD | D3: Current SPOT 2027E EV / EBITDA
A4: 2026-10-02 | B4: 472.89 | C4: 1.1259 | D4: 20.5
A7: Company | B7: Ticker | C7: Business model | D7: Currency | E7: 2025A Revenue | F7: 2026E Revenue | G7: 2027E Revenue | H7: 2026E Rev Growth | I7: 2027E Rev Growth | J7: 2026E EBITDA | K7: 2027E EBITDA | L7: 2026E EBITDA Margin | M7: 2027E EBITDA Margin | N7: 2026E EV / Revenue | O7: 2027E EV / Revenue | P7: 2026E EV / EBITDA | Q7: 2027E EV / EBITDA | R7: 2027E P/E
A8: Spotify Technology | B8: SPOT | C8: Global audio streaming platform | D8: EUR | E8: 17186 | F8: 19537 | G8: 22357 | H8: =F8/E8-1 -> 0.13679739 | I8: =G8/F8-1 -> 0.14434151 | J8: 2989 | K8: 3827 | L8: =J8/F8 -> 0.15299176 | M8: =K8/G8 -> 0.17117681 | N8: 4.18 | O8: 3.51 | P8: 27.3 | Q8: 20.5 | R8: 27.9
A9: Netflix | B9: NFLX | C9: Global subscription video streaming | D9: USD | E9: 45183 | F9: 51219 | G9: 56985 | H9: =F9/E9-1 -> 0.13359007 | I9: =G9/F9-1 -> 0.11257541 | J9: 17055 | K9: 20014 | L9: =J9/F9 -> 0.3329819 | M9: =K9/G9 -> 0.35121523 | N9: 5.72 | O9: 5.08 | P9: 17.2 | Q9: 14.5 | R9: 18.2
A10: Warner Music Group | B10: WMG | C10: Recorded music / publishing rights owner | D10: USD | E10: 6707 | F10: 7334 | G10: 7763 | H10: =F10/E10-1 -> 0.093484419 | I10: =G10/F10-1 -> 0.058494682 | J10: 1734 | K10: 1899 | L10: =J10/F10 -> 0.23643305 | M10: =K10/G10 -> 0.24462192 | N10: 2.58 | O10: 2.39 | P10: 10.9 | Q10: 9.77 | R10: 16.4
A11: Universal Music Group | B11: UMG | C11: Recorded music / publishing rights owner | D11: EUR | E11: 12507 | F11: 13426 | G11: 14372 | H11: =F11/E11-1 -> 0.073478852 | I11: =G11/F11-1 -> 0.070460301 | J11: 2797 | K11: 3054 | L11: =J11/F11 -> 0.20832713 | M11: =K11/G11 -> 0.21249652 | N11: 2.26 | O11: 2.08 | P11: 10.8 | Q11: 9.71 | R11: 15
A12: Tencent Music | B12: TME | C12: China music streaming / social entertainment | D12: RMB | E12: 32902 | F12: 35360 | G12: 38319 | H12: =F12/E12-1 -> 0.074706705 | I12: =G12/F12-1 -> 0.083682127 | J12: 11685 | K12: 12580 | L12: =J12/F12 -> 0.33045814 | M12: =K12/G12 -> 0.32829667 | N12: 1.64 | O12: 1.35 | P12: 4.92 | Q12: 3.99 | R12: 9.08
A13: Sirius XM | B13: SIRI | C13: Subscription audio / satellite radio | D13: USD | E13: 8558 | F13: 8590 | G13: 8712 | H13: =F13/E13-1 -> 0.0037391914 | I13: =G13/F13-1 -> 0.014202561 | J13: 2643 | K13: 2636 | L13: =J13/F13 -> 0.30768335 | M13: =K13/G13 -> 0.30257117 | N13: 2.11 | O13: 2.1 | P13: 6.8 | Q13: 6.96 | R13: 8.72
A15: Median (ex-SPOT) | H15: =MEDIAN(H9:H13) -> 0.074706705 | I15: =MEDIAN(I9:I13) -> 0.070460301 | L15: =MEDIAN(L9:L13) -> 0.30768335 | M15: =MEDIAN(M9:M13) -> 0.30257117 | N15: =MEDIAN(N9:N13) -> 2.26 | O15: =MEDIAN(O9:O13) -> 2.1 | P15: =MEDIAN(P9:P13) -> 10.8 | Q15: =MEDIAN(Q9:Q13) -> 9.71 | R15: =MEDIAN(R9:R13) -> 15
A16: Average (ex-SPOT) | H16: =AVERAGE(H9:H13) -> 0.075799847 | I16: =AVERAGE(I9:I13) -> 0.067883016 | L16: =AVERAGE(L9:L13) -> 0.28317672 | M16: =AVERAGE(M9:M13) -> 0.2878403 | N16: =AVERAGE(N9:N13) -> 2.862 | O16: =AVERAGE(O9:O13) -> 2.6 | P16: =AVERAGE(P9:P13) -> 10.124 | Q16: =AVERAGE(Q9:Q13) -> 8.986 | R16: =AVERAGE(R9:R13) -> 13.48
A19: Target Multiple Framework
A20: Metric | B20: Value
A21: SPOT current 2027E EV / EBITDA | B21: =Q8 -> 20.5
A22: 2027E ex-SPOT comp median | B22: =MEDIAN(Q9:Q13) -> 9.71
A23: 2027E music-rights median (WMG / UMG) | B23: =MEDIAN(Q10:Q11) -> 9.74
A24: 2027E Netflix EV / EBITDA | B24: =Q9 -> 14.5
A25: Selected terminal EV / EBITDA | B25: 12
A26: Premium / (discount) to ex-SPOT median | B26: =B25/B22-1 -> 0.23583934

Sheet Valuation
A1: Spotify Valuation & Cap Table
A3: Key Inputs | B3: Value | D3: Terminal Multiple Sensitivity
A4: Valuation date | B4: 2026-10-02 | D4: EV / EBITDA | E4: 9 | F4: 10 | G4: 11 | H4: 12 | I4: 13 | J4: 14.5
A5: Projection period end | B5: 2027-06-30 | D5: Implied $ / share | E5: =(($B$20*E$4)+$B$23+$B$24+$B$25)/$B$27*$B$7 -> 206.97127 | F5: =(($B$20*F$4)+$B$23+$B$24+$B$25)/$B$27*$B$7 -> 223.19825 | G5: =(($B$20*G$4)+$B$23+$B$24+$B$25)/$B$27*$B$7 -> 239.42524 | H5: =(($B$20*H$4)+$B$23+$B$24+$B$25)/$B$27*$B$7 -> 255.65223 | I5: =(($B$20*I$4)+$B$23+$B$24+$B$25)/$B$27*$B$7 -> 271.87921 | J5: =(($B$20*J$4)+$B$23+$B$24+$B$25)/$B$27*$B$7 -> 296.21969
A6: Current SPOT price ($) | B6: 472.89 | D6: Upside / (downside) | E6: =E5/$B$6-1 -> -0.56232682 | F6: =F5/$B$6-1 -> -0.52801232 | G6: =G5/$B$6-1 -> -0.49369782 | H6: =H5/$B$6-1 -> -0.45938331 | I6: =I5/$B$6-1 -> -0.42506881 | J6: =J5/$B$6-1 -> -0.37359705
A7: EUR / USD | B7: 1.1259
A8: Selected terminal EV / EBITDA | B8: ='Trading Comps'!B25 -> 12
D9: Current Market Cross-Check
D10: Current shares outstanding (mm) | E10: 205.58
A11: Terminal Operating Metrics | B11: Q2-27E LTM | D11: Current market cap ($bn) | E11: 97.22
A12: Revenue (€m) | B12: =Model!Y5 -> 20270.41 | D12: Current enterprise value ($bn) | E12: 89.77
A13: EBIT (€m) | B13: =Model!Y13 -> 2888.9705 | D13: Current 2027E EV / EBITDA | E13: 20.5
A14: D&A (€m) | B14: =Model!Y71+Model!Y72 -> 121.62246 | D14: Current 2027E P/E | E14: 27.9
A15: EBITDA (€m) | B15: =SUM(B13:B14) -> 3010.5929
A16: EBITDA margin | B16: =B15/B12 -> 0.14852156
A19: Valuation Bridge | B19: Value
A20: LTM EBITDA (€m) | B20: =B15 -> 3010.5929
A21: Terminal EV / EBITDA | B21: =B8 -> 12
A22: Implied enterprise value (€m) | B22: =B20*B21 -> 36127.115
A23: Cash & equivalents at Q2-27E (€m) | B23: =Model!S40 -> 7854.0456
A24: Short-term investments at Q2-27E (€m) | B24: =Model!S39 -> 3450
A25: Less: exchangeable notes (€m) | B25: =-(Model!S50+Model!S60) -> 0
A26: Implied equity value (€m) | B26: =SUM(B22:B25) -> 47431.161
A27: Diluted shares (mm) | B27: =Model!S24 -> 208.88824
A28: Implied value / share (€) | B28: =B26/B27 -> 227.06477
A30: Implied value / share ($) | B30: =B28*B7 -> 255.65223
A31: Downside vs. current price | B31: =B30/B6-1 -> -0.45938331

Sheet Assumptions
A1: Spotify Forecast Assumptions
A3: Driver | B3: Q3-2026E | C3: Q4-2026E | D3: Q1-2027E | E3: Q2-2027E
A4: Revenue (€m) | B4: 5000
A5: Revenue YoY growth | C5: 0.11 | D5: 0.1 | E5: 0.1
A6: Gross margin | B6: 0.329 | C6: 0.327 | D6: 0.328 | E6: 0.329
A7: Operating income (€m) | B7: 670
A8: Q3 R&D % of total Opex | B8: 0.42
A9: Q3 S&M % of total Opex | B9: 0.42
A10: Q3 G&A % of total Opex | B10: 0.16
A11: R&D % revenue | C11: 0.075 | D11: 0.076 | E11: 0.078
A12: S&M % revenue | C12: 0.08 | D12: 0.08 | E12: 0.08
A13: G&A % revenue | C13: 0.026 | D13: 0.026 | E13: 0.027
A14: Annualized interest yield on prior liquidity | B14: 0.035 | C14: 0.035 | D14: 0.035 | E14: 0.035
A15: Finance costs % revenue | B15: 0.0045 | C15: 0.0045 | D15: 0.0045 | E15: 0.0045
A16: Tax rate | B16: 0.24 | C16: 0.24 | D16: 0.24 | E16: 0.24
A17: Quarterly basic share change (mm) | B17: 0 | C17: 0 | D17: 0 | E17: 0
A18: Incremental diluted shares (mm) | B18: 3.1 | C18: 3.1 | D18: 3.1 | E18: 3.1
A19: D&A % revenue | B19: 0.005 | C19: 0.005 | D19: 0.005 | E19: 0.005
A20: Intangible amortization % revenue | B20: 0.001 | C20: 0.001 | D20: 0.001 | E20: 0.001
A21: SBC % revenue | B21: 0.016 | C21: 0.016 | D21: 0.016 | E21: 0.016
A22: Cash taxes / tax expense | B22: 0.85 | C22: 0.85 | D22: 0.85 | E22: 0.85
A23: Capex % revenue | B23: 0.0055 | C23: 0.0055 | D23: 0.0055 | E23: 0.0055
A24: Option exercise proceeds (€m) | B24: 30 | C24: 30 | D24: 30 | E24: 30
A25: Open-market buybacks (€m) | B25: 300 | C25: 300 | D25: 300 | E25: 300
... A37: Derivative liabilities (€m) | B37: 20 | C37: 20 | D37: 20 | E37: 20

Sheet Raw Numbers
A1: Spotify Reported Inputs (hardcodes; €m except per-share and shares)
A3: Annual Income Statement | B3: FY2023 | C3: FY2024 | D3: FY2025
A4: Revenue | B4: 13247 | C4: 15673 | D4: 17186
A5: Cost of revenue | B5: 9850 | C5: 10949 | D5: 11690
A6: Gross profit | B6: 3397 | C6: 4724 | D6: 5496
A7: R&D | B7: 1725 | C7: 1486 | D7: 1393
A8: Sales & marketing | B8: 1533 | C8: 1392 | D8: 1426
A9: G&A | B9: 585 | C9: 481 | D9: 479
A10: Total Opex | B10: 3843 | C10: 3359 | D10: 3298
A11: Operating income | B11: -446 | C11: 1365 | D11: 2198
A12: Finance income | B12: 161 | C12: 328 | D12: 292
A13: Finance costs | B13: -220 | C13: -352 | D13: -266
A14: Net finance | B14: -59 | C14: -24 | D14: 26
A15: Pretax income | B15: -505 | C15: 1341 | D15: 2224
... A21: Diluted WA shares | B21: 194.7323 | C21: 206.99037 | D21: 210.50917
A25: Reported Cash Flow (YTD / FY hardcodes)
A26: Line Item | B26: 2023 Q1 | C26: 2023 H1 | D26: 2023 9M | E26: 2023 FY | F26: 2024 Q1 | G26: 2024 H1 | H26: 2024 9M | I26: 2024 FY | J26: 2025 Q1 | K26: 2025 H1 | L26: 2025 9M | M26: 2025 FY | N26: 2026 Q1 | O26: 2026 H1
A27: Net income/(loss) | B27: -225 | C27: -527 | D27: -462 | E27: -532 | F27: 197 | G27: 471 | H27: 771 | I27: 1138 | J27: 225 | K27: 139 | L27: 1038 | M27: 2212 | N27: 721 | O27: 1266
A28: Depreciation - PP&E and ROU assets | B28: 31 | C28: 61 | D28: 87 | E28: 110 | F28: 22 | G28: 43 | H28: 64 | I28: 85 | J28: 20 | K28: 40 | L28: 59 | M28: 79 | N28: 20 | O28: 44
A29: Amortization of intangible assets | B29: 13 | C29: 27 | D29: 37 | E29: 48 | F29: 9 | G29: 18 | H29: 27 | I29: 36 | J29: 7 | K29: 13 | L29: 18 | M29: 23 | N29: 6 | O29: 11
A30: Impairment of real estate assets | B30: 0 | C30: 90 | D30: 90 | E30: 123 | F30: 4 | G30: 18 | H30: 18 | I30: 43 | J30: 2 | K30: 3 | L30: 8 | M30: 8 | N30: 4 | O30: 4
A31: Write-off of content assets | B31: 0 | C31: 30 | D31: 30 | E31: 29 | F31: 0 | G31: 0 | H31: 0 | I31: 0 | J31: 0 | K31: 0 | L31: 0 | M31: 0 | N31: 0 | O31: 0
A32: Share-based compensation expense | B32: 105 | C32: 202 | D32: 287 | E32: 321 | F32: 69 | G32: 150 | H32: 213 | I32: 267 | J32: 42 | K32: 115 | L32: 190 | M32: 247 | N32: 56 | O32: 142
A33: Finance income | B33: -27 | C33: -60 | D33: -115 | E33: -161 | F33: -59 | G33: -135 | H33: -201 | I33: -328 | J33: -71 | K33: -160 | L33: -422 | M33: -292 | N33: -248 | O33: -334
A34: Finance costs | B34: 77 | C34: 104 | D34: 118 | E34: 220 | F34: 53 | G34: 125 | H34: 247 | I34: 352 | J34: 252 | K34: 699 | L34: 716 | M34: 266 | N34: 26 | O34: 47
A35: Income tax expense/(benefit) | B35: 19 | C35: 80 | D35: 88 | E35: 27 | F35: -23 | G35: -27 | H35: 71 | I35: 203 | J35: 103 | K35: 237 | L35: 165 | M35: 12 | N35: 216 | O35: 391
A36: Other non-cash items | B36: -5 | C36: -3 | D36: -4 | E36: 1 | F36: 0 | G36: -1 | H36: -1 | I36: 2 | J36: 0 | K36: 8 | L36: 9 | M36: 10 | N36: -2 | O36: -1
A37: Change in trade receivables & other assets | B37: 118 | C37: 21 | D37: -48 | E37: -145 | F37: 80 | G37: 120 | H37: 116 | I37: 145 | J37: -4 | K37: -23 | L37: -49 | M37: -115 | N37: 91 | O37: 11
A38: Change in trade & other liabilities | B38: -57 | C38: 20 | D38: 82 | E38: 501 | F38: -171 | G38: -143 | H38: -57 | I38: 183 | J38: -90 | K38: 111 | L38: 211 | M38: 281 | N38: -94 | O38: 56
... A65: Supplemental: ROU assets recognized | B65: 15 | C65: 0 | D65: 22 | E65: 0 | F65: 13 | G65: 0 | H65: 0 | I65: 0 | J65: 18 | K65: 0 | L65: 0 | M65: 0 | N65: 0 | O65: 0
